{"nm":"09- Female accountant","mn":"","layers":[{"ty":0,"nm":"Human Scene - 09","mn":"","sr":1,"st":0,"op":180,"ip":0,"hd":false,"cl":"","ln":"","ddd":0,"bm":0,"hasMask":false,"ao":0,"ks":{"a":{"a":0,"k":[450,450,0],"ix":1},"s":{"a":0,"k":[100,100,100],"ix":6},"sk":{"a":0,"k":0},"p":{"a":0,"k":[520,680,0],"ix":2},"r":{"a":0,"k":0,"ix":10},"sa":{"a":0,"k":0},"o":{"a":0,"k":100,"ix":11}},"ef":[],"w":900,"h":900,"refId":"comp_0","ind":1},{"ty":0,"nm":"Background- 09","mn":"","sr":1,"st":0,"op":180,"ip":0,"hd":false,"cl":"","ln":"","ddd":0,"bm":0,"hasMask":false,"ao":0,"ks":{"a":{"a":0,"k":[600,600,0],"ix":1},"s":{"a":0,"k":[100,100,100],"ix":6},"sk":{"a":0,"k":0},"p":{"a":0,"k":[600,600,0],"ix":2},"r":{"a":0,"k":0,"ix":10},"sa":{"a":0,"k":0},"o":{"a":0,"k":100,"ix":11}},"ef":[],"w":1200,"h":1200,"refId":"comp_1","ind":2}],"ddd":0,"h":1200,"w":1200,"meta":{"a":"","k":"","d":"","g":"@lottiefiles/toolkit-js 0.22.1","tc":"#000000"},"v":"5.6.2","fr":30,"op":180,"ip":0,"assets":[{"nm":"","mn":"","layers":[{"ty":4,"nm":"head","mn":"","sr":1,"st":0,"op":180,"ip":0,"hd":false,"cl":"","ln":"","ddd":0,"bm":0,"hasMask":false,"ao":0,"ks":{"a":{"a":0,"k":[674.103,407.495,0],"ix":1},"s":{"a":0,"k":[100,100,100],"ix":6},"sk":{"a":0,"k":0},"p":{"a":0,"k":[674.103,407.495,0],"ix":2},"r":{"a":1,"k":[{"o":{"x":0.333,"y":0},"i":{"x":0.667,"y":1},"s":[-5],"t":0},{"o":{"x":0.333,"y":0},"i":{"x":0.667,"y":1},"s":[7],"t":30},{"o":{"x":0.333,"y":0},"i":{"x":0.667,"y":1},"s":[-5],"t":60},{"o":{"x":0.333,"y":0},"i":{"x":0.667,"y":1},"s":[7],"t":75},{"o":{"x":0.333,"y":0},"i":{"x":0.667,"y":1},"s":[-5],"t":90},{"o":{"x":0.333,"y":0},"i":{"x":0.667,"y":1},"s":[3],"t":105},{"o":{"x":0.167,"y":0},"i":{"x":0.667,"y":1},"s":[-5],"t":120},{"o":{"x":0.333,"y":0},"i":{"x":0.667,"y":1},"s":[7],"t":150},{"o":{"x":0.167,"y":0.167},"i":{"x":0.833,"y":0.833},"s":[-5],"t":179}],"ix":10},"sa":{"a":0,"k":0},"o":{"a":0,"k":100,"ix":11}},"ef":[],"shapes":[{"ty":"gr","bm":0,"cl":"","ln":"","hd":false,"mn":"ADBE Vector Group","nm":"Group 1","ix":1,"cix":2,"np":3,"it":[{"ty":"sh","bm":0,"cl":"","ln":"","hd":false,"mn":"ADBE Vector Shape - Group","nm":"Path 1","ix":1,"d":1,"ks":{"a":0,"k":{"c":true,"i":[[0.489,0.061],[4.822,6.487],[-1.837,10.829],[8.671,3.99],[6.596,-7.597],[0.136,-0.215],[-0.018,-0.197],[-1.172,-4.236],[-0.238,-0.744],[-0.417,-1.072],[-0.328,-0.741],[-0.275,-0.564],[-10.8,-2.124],[-0.845,-1.187],[-0.289,0],[-0.01,0.001],[-1.006,0.078],[-0.718,0.074],[-7.763,2.936],[-1.696,13.641]],"o":[[-6.345,-0.792],[-6.689,-8.996],[1.972,-11.627],[-6.882,-3.167],[-18.676,-10.779],[-0.107,0.167],[0.02,0.2],[0.191,0.686],[0.319,0.995],[0.278,0.718],[0.246,0.556],[5.318,10.905],[-8.65,22.914],[0.168,0.235],[0.009,0],[0.024,0],[0.51,-0.04],[4.25,-0.445],[15.568,-5.89],[0.062,-0.491]],"v":[[44.904,19.486],[27.588,8.198],[19.721,-23.945],[7.97,-51.337],[-13.188,-44.363],[-45.585,-34.07],[-45.722,-33.507],[-44.236,-26.072],[-43.595,-23.924],[-42.495,-20.817],[-41.585,-18.626],[-40.805,-16.945],[-16.192,2.938],[-4.545,54.767],[-3.817,55.142],[-3.789,55.142],[-2.183,55.043],[-0.331,54.873],[19.288,50.337],[45.679,20.485]]},"ix":2}},{"ty":"st","bm":0,"cl":"","ln":"","hd":false,"mn":"ADBE Vector Graphic - Stroke","nm":"Stroke 1","lc":1,"lj":1,"ml":10,"o":{"a":0,"k":100,"ix":4},"w":{"a":0,"k":1.5,"ix":5},"d":[],"c":{"a":0,"k":[0.0588,0.0902,0.1647],"ix":3}},{"ty":"fl","bm":0,"cl":"","ln":"","hd":false,"mn":"ADBE Vector Graphic - Fill","nm":"Fill 1","c":{"a":0,"k":[0.0588,0.0902,0.1647],"ix":4},"r":1,"o":{"a":0,"k":100,"ix":5}},{"ty":"tr","a":{"a":0,"k":[0,0],"ix":1},"s":{"a":0,"k":[100,100],"ix":3},"sk":{"a":0,"k":0,"ix":4},"p":{"a":0,"k":[694.147,366.353],"ix":2},"r":{"a":0,"k":0,"ix":6},"sa":{"a":0,"k":0,"ix":5},"o":{"a":0,"k":100,"ix":7}}]},{"ty":"gr","bm":0,"cl":"","ln":"","hd":false,"mn":"ADBE Vector Group","nm":"Group 2","ix":2,"cix":2,"np":2,"it":[{"ty":"sh","bm":0,"cl":"","ln":"","hd":false,"mn":"ADBE Vector Shape - Group","nm":"Path 1","ix":1,"d":1,"ks":{"a":0,"k":{"c":false,"i":[[0,0],[-0.834,3.498],[30.636,-8.013],[-3.466,-16.507],[0,0]],"o":[[3.004,-2.284],[6.835,-28.634],[-30.637,8.013],[4.813,22.919],[0,0]],"v":[[26.53,37.652],[32.091,28.465],[-2.289,-39.824],[-35.461,24.918],[-1.357,44.541]]},"ix":2}},{"ty":"st","bm":0,"cl":"","ln":"","hd":false,"mn":"ADBE Vector Graphic - Stroke","nm":"Stroke 1","lc":2,"lj":2,"ml":1,"o":{"a":0,"k":100,"ix":4},"w":{"a":0,"k":2,"ix":5},"d":[],"c":{"a":0,"k":[0.0588,0.0902,0.1647],"ix":3}},{"ty":"tr","a":{"a":0,"k":[0,0],"ix":1},"s":{"a":0,"k":[100,100],"ix":3},"sk":{"a":0,"k":0,"ix":4},"p":{"a":0,"k":[676.709,363.063],"ix":2},"r":{"a":0,"k":0,"ix":6},"sa":{"a":0,"k":0,"ix":5},"o":{"a":0,"k":100,"ix":7}}]},{"ty":"gr","bm":0,"cl":"","ln":"","hd":false,"mn":"ADBE Vector Group","nm":"Group 3","ix":3,"cix":2,"np":2,"it":[{"ty":"sh","bm":0,"cl":"","ln":"","hd":false,"mn":"ADBE Vector Shape - Group","nm":"Path 1","ix":1,"d":1,"ks":{"a":0,"k":{"c":true,"i":[[30.637,-8.013],[-1.894,-16.763],[0,0],[-11.238,5.969],[-0.835,3.498]],"o":[[-30.637,8.013],[1.896,16.763],[0,0],[3.004,-2.284],[6.835,-28.634]],"v":[[-3.075,-38.61],[-36.247,26.132],[-10.557,46.622],[25.743,38.866],[31.306,29.679]]},"ix":2}},{"ty":"fl","bm":0,"cl":"","ln":"","hd":false,"mn":"ADBE Vector Graphic - Fill","nm":"Fill 1","c":{"a":0,"k":[1,1,1],"ix":4},"r":1,"o":{"a":0,"k":100,"ix":5}},{"ty":"tr","a":{"a":0,"k":[0,0],"ix":1},"s":{"a":0,"k":[100,100],"ix":3},"sk":{"a":0,"k":0,"ix":4},"p":{"a":0,"k":[677.495,361.849],"ix":2},"r":{"a":0,"k":0,"ix":6},"sa":{"a":0,"k":0,"ix":5},"o":{"a":0,"k":100,"ix":7}}]}],"ind":1,"parent":5},{"ty":4,"nm":"arm L","mn":"","sr":1,"st":0,"op":180,"ip":0,"hd":false,"cl":"","ln":"","ddd":0,"bm":0,"hasMask":false,"ao":0,"ks":{"a":{"a":0,"k":[715.492,442.614,0],"ix":1},"s":{"a":0,"k":[100,100,100],"ix":6},"sk":{"a":0,"k":0},"p":{"a":0,"k":[715.492,442.614,0],"ix":2},"r":{"a":1,"k":[{"o":{"x":0.5,"y":0},"i":{"x":0.5,"y":1},"s":[4],"t":0},{"o":{"x":0.5,"y":0},"i":{"x":0.667,"y":1},"s":[-6],"t":30},{"o":{"x":0.333,"y":0},"i":{"x":0.833,"y":1},"s":[-5],"t":60},{"o":{"x":0.167,"y":0},"i":{"x":0.833,"y":1},"s":[-4],"t":90},{"o":{"x":0.167,"y":0},"i":{"x":0.833,"y":1},"s":[2],"t":120},{"o":{"x":0.167,"y":0},"i":{"x":0.5,"y":1},"s":[-4],"t":150},{"o":{"x":0.167,"y":0.167},"i":{"x":0.833,"y":0.833},"s":[4],"t":179}],"ix":10},"sa":{"a":0,"k":0},"o":{"a":0,"k":100,"ix":11}},"ef":[],"shapes":[{"ty":"gr","bm":0,"cl":"","ln":"","hd":false,"mn":"ADBE Vector Group","nm":"Group 1","ix":1,"cix":2,"np":2,"it":[{"ty":"sh","bm":0,"cl":"","ln":"","hd":false,"mn":"ADBE Vector Shape - Group","nm":"Path 1","ix":1,"d":1,"ks":{"a":0,"k":{"c":true,"i":[[-3.159,-28.43],[-10.914,-17.862],[8.491,31.953],[14.685,-0.048]],"o":[[2.685,24.166],[15.392,25.191],[-9.301,-35.002],[-10.571,0.035]],"v":[[-49.111,-36.028],[-2.766,47.031],[43.779,39.521],[-29.794,-72.174]]},"ix":2}},{"ty":"fl","bm":0,"cl":"","ln":"","hd":false,"mn":"ADBE Vector Graphic - Fill","nm":"Fill 1","c":{"a":0,"k":[0.0588,0.0902,0.1647],"ix":4},"r":1,"o":{"a":0,"k":100,"ix":5}},{"ty":"tr","a":{"a":0,"k":[0,0],"ix":1},"s":{"a":0,"k":[100,100],"ix":3},"sk":{"a":0,"k":0,"ix":4},"p":{"a":0,"k":[744.828,503.792],"ix":2},"r":{"a":0,"k":0,"ix":6},"sa":{"a":0,"k":0,"ix":5},"o":{"a":0,"k":100,"ix":7}}]}],"ind":2,"parent":5},{"ty":4,"nm":"arm L","mn":"","sr":1,"st":0,"op":180,"ip":0,"hd":false,"cl":"","ln":"","ddd":0,"bm":0,"hasMask":false,"ao":0,"ks":{"a":{"a":0,"k":[772.097,552.914,0],"ix":1},"s":{"a":0,"k":[100,100,100],"ix":6},"sk":{"a":0,"k":0},"p":{"a":0,"k":[772.097,552.914,0],"ix":2},"r":{"a":1,"k":[{"o":{"x":0.5,"y":0},"i":{"x":0.5,"y":1},"s":[-11],"t":0},{"o":{"x":0.5,"y":0},"i":{"x":0.5,"y":1},"s":[6],"t":30},{"o":{"x":0.5,"y":0},"i":{"x":0.833,"y":1},"s":[-11],"t":60},{"o":{"x":0.167,"y":0},"i":{"x":0.833,"y":1},"s":[-9],"t":90},{"o":{"x":0.167,"y":0},"i":{"x":0.833,"y":1},"s":[-19],"t":120},{"o":{"x":0.167,"y":0},"i":{"x":0.5,"y":1},"s":[-9],"t":150},{"o":{"x":0.167,"y":0.167},"i":{"x":0.833,"y":0.833},"s":[-11],"t":179}],"ix":10},"sa":{"a":0,"k":0},"o":{"a":0,"k":100,"ix":11}},"ef":[],"shapes":[{"ty":"gr","bm":0,"cl":"","ln":"","hd":false,"mn":"ADBE Vector Group","nm":"Group 1","ix":1,"cix":2,"np":2,"it":[{"ty":"sh","bm":0,"cl":"","ln":"","hd":false,"mn":"ADBE Vector Shape - Group","nm":"Path 1","ix":1,"d":1,"ks":{"a":0,"k":{"c":true,"i":[[1.09,-26.297],[-0.058,-0.339],[-7.725,6.519],[1.928,31.433],[3.556,7.691],[9.94,-1.227]],"o":[[-0.632,15.25],[1.758,10.243],[3.214,-2.713],[-0.59,-9.641],[-3.678,-7.957],[-8.748,1.079]],"v":[[-23.159,-50.241],[-20.385,66.527],[6.699,76.205],[21.863,-38.007],[17.001,-71.97],[-4.895,-81.497]]},"ix":2}},{"ty":"fl","bm":0,"cl":"","ln":"","hd":false,"mn":"ADBE Vector Graphic - Fill","nm":"Fill 1","c":{"a":0,"k":[0.0588,0.0902,0.1647],"ix":4},"r":1,"o":{"a":0,"k":100,"ix":5}},{"ty":"tr","a":{"a":0,"k":[0,0],"ix":1},"s":{"a":0,"k":[100,100],"ix":3},"sk":{"a":0,"k":0,"ix":4},"p":{"a":0,"k":[772.194,617.836],"ix":2},"r":{"a":0,"k":0,"ix":6},"sa":{"a":0,"k":0,"ix":5},"o":{"a":0,"k":100,"ix":7}}]}],"ind":3,"parent":2},{"ty":4,"nm":"arm L","mn":"","sr":1,"st":0,"op":180,"ip":0,"hd":false,"cl":"","ln":"","ddd":0,"bm":0,"hasMask":false,"ao":0,"ks":{"a":{"a":0,"k":[768.394,682.015,0],"ix":1},"s":{"a":0,"k":[100,100,100],"ix":6},"sk":{"a":0,"k":0},"p":{"a":0,"k":[768.394,682.015,0],"ix":2},"r":{"a":1,"k":[{"o":{"x":0.5,"y":0},"i":{"x":0.5,"y":1},"s":[5],"t":0},{"o":{"x":0.5,"y":0},"i":{"x":0.5,"y":1},"s":[-7],"t":30},{"o":{"x":0.5,"y":0},"i":{"x":0.833,"y":1},"s":[5],"t":60},{"o":{"x":0.167,"y":0},"i":{"x":0.833,"y":1},"s":[7],"t":90},{"o":{"x":0.167,"y":0},"i":{"x":0.833,"y":1},"s":[3],"t":120},{"o":{"x":0.167,"y":0},"i":{"x":0.5,"y":1},"s":[7],"t":150},{"o":{"x":0.167,"y":0.167},"i":{"x":0.833,"y":0.833},"s":[5],"t":179}],"ix":10},"sa":{"a":0,"k":0},"o":{"a":0,"k":100,"ix":11}},"ef":[],"shapes":[{"ty":"gr","bm":0,"cl":"","ln":"","hd":false,"mn":"ADBE Vector Group","nm":"Group 1","ix":1,"cix":2,"np":3,"it":[{"ty":"sh","bm":0,"cl":"","ln":"","hd":false,"mn":"ADBE Vector Shape - Group","nm":"Path 1","ix":1,"d":1,"ks":{"a":0,"k":{"c":true,"i":[[0.497,2.222],[4.98,2.32],[0.89,0.402],[2.028,5.535],[0.018,0.859],[12.097,-11.149],[3.43,-8.392],[1.751,-2.787],[-0.895,-1.769],[-0.846,-0.204],[0,0],[-3.575,2.934],[-2.912,-0.781],[-2.356,-2.153],[-5.403,-2.137],[-2.961,-0.018],[-3.092,1.653],[-0.488,1.33]],"o":[[-0.815,-3.639],[-0.808,-0.376],[-6.485,-2.925],[-0.3,-0.817],[-0.598,-0.1],[-3.381,4.463],[-1.501,3.676],[-2.478,3.945],[0.316,0.625],[0,0],[2.829,-0.627],[4.237,-3.475],[1.921,0.511],[3.094,2.826],[0,0],[2.293,0.015],[1.957,-1.047],[0.607,-1.653]],"v":[[36.134,17.448],[27.4,8.468],[24.842,7.302],[8.257,-4.797],[7.891,-15.566],[-12.746,-17.226],[-27.086,6.031],[-32.516,15.964],[-35.736,24.283],[-33.985,25.528],[-31.724,25.528],[-21.921,19.19],[-9.975,12.552],[-3.662,17.076],[8.673,25.528],[20.175,28.361],[32.727,26.551],[35.642,23.395]]},"ix":2}},{"ty":"st","bm":0,"cl":"","ln":"","hd":false,"mn":"ADBE Vector Graphic - Stroke","nm":"Stroke 1","lc":1,"lj":2,"ml":1,"o":{"a":0,"k":100,"ix":4},"w":{"a":0,"k":1.5,"ix":5},"d":[],"c":{"a":0,"k":[0.0588,0.0902,0.1647],"ix":3}},{"ty":"fl","bm":0,"cl":"","ln":"","hd":false,"mn":"ADBE Vector Graphic - Fill","nm":"Fill 1","c":{"a":0,"k":[1,1,1],"ix":4},"r":1,"o":{"a":0,"k":100,"ix":5}},{"ty":"tr","a":{"a":0,"k":[0,0],"ix":1},"s":{"a":0,"k":[100,100],"ix":3},"sk":{"a":0,"k":0,"ix":4},"p":{"a":0,"k":[768.205,703.819],"ix":2},"r":{"a":0,"k":0,"ix":6},"sa":{"a":0,"k":0,"ix":5},"o":{"a":0,"k":100,"ix":7}}]}],"ind":4,"parent":3},{"ty":4,"nm":"body","mn":"","sr":1,"st":0,"op":180,"ip":0,"hd":false,"cl":"","ln":"","ddd":0,"bm":0,"hasMask":false,"ao":0,"ks":{"a":{"a":0,"k":[672.313,584.119,0],"ix":1},"s":{"a":0,"k":[100,100,100],"ix":6},"sk":{"a":0,"k":0},"p":{"a":0,"k":[582.313,354.119,0],"ix":2},"r":{"a":1,"k":[{"o":{"x":0.55,"y":0},"i":{"x":0.45,"y":1},"s":[-2],"t":0},{"o":{"x":0.55,"y":0},"i":{"x":0.45,"y":1},"s":[3],"t":30},{"o":{"x":0.55,"y":0},"i":{"x":0.45,"y":1},"s":[-2],"t":60},{"o":{"x":0.55,"y":0},"i":{"x":0.45,"y":1},"s":[3],"t":90},{"o":{"x":0.55,"y":0},"i":{"x":0.45,"y":1},"s":[0],"t":120},{"o":{"x":0.55,"y":0},"i":{"x":0.45,"y":1},"s":[3],"t":150},{"o":{"x":0.167,"y":0.167},"i":{"x":0.833,"y":0.833},"s":[-2],"t":179}],"ix":10},"sa":{"a":0,"k":0},"o":{"a":0,"k":100,"ix":11}},"ef":[],"shapes":[{"ty":"gr","bm":0,"cl":"","ln":"","hd":false,"mn":"ADBE Vector Group","nm":"Group 1","ix":1,"cix":2,"np":3,"it":[{"ty":"sh","bm":0,"cl":"","ln":"","hd":false,"mn":"ADBE Vector Shape - Group","nm":"Path 1","ix":1,"d":1,"ks":{"a":0,"k":{"c":true,"i":[[2.762,6.163],[0,0],[7.01,-0.206],[0,0],[-12.435,-15.734],[-18.548,33.1]],"o":[[-2.425,-5.411],[-8.816,-0.075],[1.408,10.893],[0,0],[12.434,15.733],[0,0]],"v":[[30.081,-25.406],[26.358,-47.518],[0.919,-47.492],[-12.52,-11.913],[-24.324,31.965],[36.759,-16.525]]},"ix":2}},{"ty":"st","bm":0,"cl":"","ln":"","hd":false,"mn":"ADBE Vector Graphic - Stroke","nm":"Stroke 1","lc":2,"lj":2,"ml":1,"o":{"a":0,"k":100,"ix":4},"w":{"a":0,"k":2,"ix":5},"d":[],"c":{"a":0,"k":[0.0588,0.0902,0.1647],"ix":3}},{"ty":"fl","bm":0,"cl":"","ln":"","hd":false,"mn":"ADBE Vector Graphic - Fill","nm":"Fill 1","c":{"a":0,"k":[1,1,1],"ix":4},"r":1,"o":{"a":0,"k":100,"ix":5}},{"ty":"tr","a":{"a":0,"k":[0,0],"ix":1},"s":{"a":0,"k":[100,100],"ix":3},"sk":{"a":0,"k":0,"ix":4},"p":{"a":0,"k":[662.626,442.373],"ix":2},"r":{"a":0,"k":0,"ix":6},"sa":{"a":0,"k":0,"ix":5},"o":{"a":0,"k":100,"ix":7}}]},{"ty":"gr","bm":0,"cl":"","ln":"","hd":false,"mn":"ADBE Vector Group","nm":"Group 2","ix":2,"cix":2,"np":3,"it":[{"ty":"sh","bm":0,"cl":"","ln":"","hd":false,"mn":"ADBE Vector Shape - Group","nm":"Path 1","ix":1,"d":1,"ks":{"a":0,"k":{"c":true,"i":[[29.107,34.667],[5.793,-0.076],[13.49,-3.467],[2.889,-1.566],[0.419,-0.452],[5.406,-14.083],[-1.322,-15.096],[-0.067,-0.613],[-5.027,-10.839],[-0.024,-0.036],[-2.425,-9.312],[-0.186,-0.752],[-0.076,-0.309],[-3.604,-2.981],[-4.346,-0.337],[-9.286,0],[-2.554,5.569],[-0.254,0.574],[-3.989,18.006]],"o":[[-2.661,-2.981],[-11.79,-0.463],[-4.961,1.762],[-3.59,1.945],[-2.401,2.586],[-3.561,9.274],[0.053,0.604],[1.011,9.263],[0.019,0.04],[4.796,7.317],[0.205,0.786],[0.078,0.316],[1.161,4.763],[3.312,2.738],[9.338,0.724],[16.681,0],[0.306,-0.656],[6.063,-13.701],[0,0]],"v":[[38.025,-73.101],[20.623,-78.938],[-26.903,-74.258],[-37.515,-70.084],[-45.216,-64.685],[-60.663,-39.094],[-65.81,-2.081],[-65.633,-0.258],[-56.982,29.995],[-56.918,30.109],[-46.028,58.162],[-45.441,60.469],[-45.205,61.417],[-37.739,73.305],[-26.009,78.135],[2.699,79.401],[36.039,72.086],[37.723,68.383],[53.603,19.289]]},"ix":2}},{"ty":"st","bm":0,"cl":"","ln":"","hd":false,"mn":"ADBE Vector Graphic - Stroke","nm":"Stroke 1","lc":1,"lj":1,"ml":10,"o":{"a":0,"k":100,"ix":4},"w":{"a":0,"k":1.5,"ix":5},"d":[],"c":{"a":0,"k":[0.0588,0.0902,0.1647],"ix":3}},{"ty":"fl","bm":0,"cl":"","ln":"","hd":false,"mn":"ADBE Vector Graphic - Fill","nm":"Fill 1","c":{"a":0,"k":[1,1,1],"ix":4},"r":1,"o":{"a":0,"k":100,"ix":5}},{"ty":"tr","a":{"a":0,"k":[0,0],"ix":1},"s":{"a":0,"k":[100,100],"ix":3},"sk":{"a":0,"k":0,"ix":4},"p":{"a":0,"k":[677.009,504.719],"ix":2},"r":{"a":0,"k":0,"ix":6},"sa":{"a":0,"k":0,"ix":5},"o":{"a":0,"k":100,"ix":7}}]}],"ind":5},{"ty":4,"nm":"leg L","mn":"","sr":1,"st":0,"op":180,"ip":0,"hd":false,"cl":"","ln":"","ddd":0,"bm":0,"hasMask":false,"ao":0,"ks":{"a":{"a":0,"k":[712,574,0],"ix":1},"s":{"a":0,"k":[100,100,100],"ix":6},"sk":{"a":0,"k":0},"p":{"a":0,"k":[622,344,0],"ix":2},"r":{"a":1,"k":[{"o":{"x":0.333,"y":0},"i":{"x":0.667,"y":1},"s":[4],"t":7},{"o":{"x":0.167,"y":0},"i":{"x":0.833,"y":1},"s":[0],"t":37},{"o":{"x":0.167,"y":0},"i":{"x":0.667,"y":1},"s":[-3],"t":67},{"o":{"x":0.167,"y":0},"i":{"x":0.833,"y":1},"s":[0],"t":97},{"o":{"x":0.167,"y":0},"i":{"x":0.833,"y":1},"s":[-2],"t":126},{"o":{"x":0.167,"y":0.167},"i":{"x":0.833,"y":0.833},"s":[4],"t":156}],"ix":10},"sa":{"a":0,"k":0},"o":{"a":0,"k":100,"ix":11}},"ef":[],"shapes":[{"ty":"gr","bm":0,"cl":"","ln":"","hd":false,"mn":"ADBE Vector Group","nm":"Group 1","ix":1,"cix":2,"np":2,"it":[{"ty":"sh","bm":0,"cl":"","ln":"","hd":false,"mn":"ADBE Vector Shape - Group","nm":"Path 1","ix":1,"d":1,"ks":{"a":0,"k":{"c":false,"i":[[0,0],[38.624,-0.511],[41.736,-23.236],[4.518,-18.522]],"o":[[-8.609,-1.256],[-35.609,0.47],[-12.904,7.184],[0,0]],"v":[[100.273,-29.9],[53.261,-31.44],[-75.292,-2.297],[-100.273,31.951]]},"ix":2}},{"ty":"st","bm":0,"cl":"","ln":"","hd":false,"mn":"ADBE Vector Graphic - Stroke","nm":"Stroke 1","lc":1,"lj":1,"ml":10,"o":{"a":0,"k":100,"ix":4},"w":{"a":0,"k":1.5,"ix":5},"d":[],"c":{"a":0,"k":[0.0588,0.0902,0.1647],"ix":3}},{"ty":"tr","a":{"a":0,"k":[0,0],"ix":1},"s":{"a":0,"k":[100,100],"ix":3},"sk":{"a":0,"k":0,"ix":4},"p":{"a":0,"k":[516.846,653.413],"ix":2},"r":{"a":0,"k":0,"ix":6},"sa":{"a":0,"k":0,"ix":5},"o":{"a":0,"k":100,"ix":7}}]},{"ty":"gr","bm":0,"cl":"","ln":"","hd":false,"mn":"ADBE Vector Group","nm":"Group 2","ix":2,"cix":2,"np":2,"it":[{"ty":"sh","bm":0,"cl":"","ln":"","hd":false,"mn":"ADBE Vector Shape - Group","nm":"Path 1","ix":1,"d":1,"ks":{"a":0,"k":{"c":false,"i":[[0,0],[-7.932,-0.636],[0,0],[-28.629,6.576],[-15.227,32.539],[10.749,16.66],[5.591,4.89],[24.318,-14.965]],"o":[[7.993,1.159],[1.628,0.139],[0.298,0.014],[26.322,-6.047],[15.199,-32.483],[-6.604,-10.236],[-9.598,-8.454],[0,0]],"v":[[-140.703,85.542],[-116.582,88.092],[-4.888,87.841],[49.384,82.465],[125.505,29.843],[120.331,-45.976],[100.315,-68.919],[19.329,-74.076]]},"ix":2}},{"ty":"st","bm":0,"cl":"","ln":"","hd":false,"mn":"ADBE Vector Graphic - Stroke","nm":"Stroke 1","lc":1,"lj":1,"ml":10,"o":{"a":0,"k":100,"ix":4},"w":{"a":0,"k":1.5,"ix":5},"d":[],"c":{"a":0,"k":[0.0588,0.0902,0.1647],"ix":3}},{"ty":"tr","a":{"a":0,"k":[0,0],"ix":1},"s":{"a":0,"k":[100,100],"ix":3},"sk":{"a":0,"k":0,"ix":4},"p":{"a":0,"k":[613.653,643.724],"ix":2},"r":{"a":0,"k":0,"ix":6},"sa":{"a":0,"k":0,"ix":5},"o":{"a":0,"k":100,"ix":7}}]},{"ty":"gr","bm":0,"cl":"","ln":"","hd":false,"mn":"ADBE Vector Group","nm":"Group 3","ix":3,"cix":2,"np":2,"it":[{"ty":"sh","bm":0,"cl":"","ln":"","hd":false,"mn":"ADBE Vector Shape - Group","nm":"Path 1","ix":1,"d":1,"ks":{"a":0,"k":{"c":true,"i":[[10.749,16.66],[5.591,4.89],[24.318,-14.965],[0.491,0.072],[38.624,-0.511],[41.736,-23.236],[4.517,-18.522],[-37.301,-2.99],[0,0],[-28.629,6.576],[-15.227,32.539]],"o":[[-6.604,-10.236],[-9.597,-8.454],[0,0],[-8.61,-1.256],[-35.609,0.47],[-12.904,7.184],[0,37.83],[1.628,0.14],[0.298,0.014],[26.321,-6.047],[15.199,-32.483]],"v":[[148.52,-45.976],[128.503,-68.919],[47.518,-74.076],[31.654,-20.21],[-15.357,-21.75],[-143.91,7.393],[-168.891,41.64],[-88.393,88.092],[23.299,87.841],[77.574,82.465],[153.693,29.843]]},"ix":2}},{"ty":"fl","bm":0,"cl":"","ln":"","hd":false,"mn":"ADBE Vector Graphic - Fill","nm":"Fill 1","c":{"a":0,"k":[1,1,1],"ix":4},"r":1,"o":{"a":0,"k":100,"ix":5}},{"ty":"tr","a":{"a":0,"k":[0,0],"ix":1},"s":{"a":0,"k":[100,100],"ix":3},"sk":{"a":0,"k":0,"ix":4},"p":{"a":0,"k":[585.465,643.724],"ix":2},"r":{"a":0,"k":0,"ix":6},"sa":{"a":0,"k":0,"ix":5},"o":{"a":0,"k":100,"ix":7}}]}],"ind":6},{"ty":4,"nm":"leg L","mn":"","sr":1,"st":0,"op":180,"ip":0,"hd":false,"cl":"","ln":"","ddd":0,"bm":0,"hasMask":false,"ao":0,"ks":{"a":{"a":0,"k":[448,687,0],"ix":1},"s":{"a":0,"k":[100,100,100],"ix":6},"sk":{"a":0,"k":0},"p":{"a":0,"k":[448,687,0],"ix":2},"r":{"a":1,"k":[{"o":{"x":0.333,"y":0},"i":{"x":0.667,"y":1},"s":[-12],"t":7},{"o":{"x":0.167,"y":0},"i":{"x":0.833,"y":1},"s":[0],"t":37},{"o":{"x":0.167,"y":0},"i":{"x":0.667,"y":1},"s":[-2],"t":67},{"o":{"x":0.167,"y":0},"i":{"x":0.833,"y":1},"s":[0],"t":97},{"o":{"x":0.167,"y":0},"i":{"x":0.833,"y":1},"s":[-2],"t":126},{"o":{"x":0.167,"y":0.167},"i":{"x":0.833,"y":0.833},"s":[-12],"t":156}],"ix":10},"sa":{"a":0,"k":0},"o":{"a":0,"k":100,"ix":11}},"ef":[],"shapes":[{"ty":"gr","bm":0,"cl":"","ln":"","hd":false,"mn":"ADBE Vector Group","nm":"Group 1","ix":1,"cix":2,"np":3,"it":[{"ty":"sh","bm":0,"cl":"","ln":"","hd":false,"mn":"ADBE Vector Shape - Group","nm":"Path 1","ix":1,"d":1,"ks":{"a":0,"k":{"c":true,"i":[[13.41,-48.846],[0.415,-9.493],[-9.743,-39.403],[-2.03,-4.755],[-23.329,8.225],[10.018,60.993],[0.064,0.411]],"o":[[-1.859,7.623],[-1.147,26.224],[16.019,64.781],[2.584,1.274],[10.367,-22.082],[-7.624,-46.415],[-14.57,-93.727]],"v":[[-51.572,-110.408],[-56.188,-80.308],[-43.232,18.596],[0.368,148.529],[46.781,151.029],[47.316,24.07],[30.652,-63.078]]},"ix":2}},{"ty":"st","bm":0,"cl":"","ln":"","hd":false,"mn":"ADBE Vector Graphic - Stroke","nm":"Stroke 1","lc":1,"lj":1,"ml":10,"o":{"a":0,"k":100,"ix":4},"w":{"a":0,"k":1.5,"ix":5},"d":[],"c":{"a":0,"k":[0.0588,0.0902,0.1647],"ix":3}},{"ty":"fl","bm":0,"cl":"","ln":"","hd":false,"mn":"ADBE Vector Graphic - Fill","nm":"Fill 1","c":{"a":0,"k":[1,1,1],"ix":4},"r":1,"o":{"a":0,"k":100,"ix":5}},{"ty":"tr","a":{"a":0,"k":[0,0],"ix":1},"s":{"a":0,"k":[100,100],"ix":3},"sk":{"a":0,"k":0,"ix":4},"p":{"a":0,"k":[468.146,795.771],"ix":2},"r":{"a":0,"k":0,"ix":6},"sa":{"a":0,"k":0,"ix":5},"o":{"a":0,"k":100,"ix":7}}]}],"ind":7,"parent":6},{"ty":4,"nm":"shoe L","mn":"","sr":1,"st":0,"op":180,"ip":0,"hd":false,"cl":"","ln":"","ddd":0,"bm":0,"hasMask":false,"ao":0,"ks":{"a":{"a":0,"k":[492.99,935.146,0],"ix":1},"s":{"a":0,"k":[100,100,100],"ix":6},"sk":{"a":0,"k":0},"p":{"a":0,"k":[492.99,935.146,0],"ix":2},"r":{"a":1,"k":[{"o":{"x":0.333,"y":0},"i":{"x":0.667,"y":1},"s":[-7],"t":7},{"o":{"x":0.167,"y":0},"i":{"x":0.833,"y":1},"s":[-12],"t":37},{"o":{"x":0.167,"y":0},"i":{"x":0.667,"y":1},"s":[-18],"t":67},{"o":{"x":0.167,"y":0},"i":{"x":0.833,"y":1},"s":[-8],"t":97},{"o":{"x":0.167,"y":0},"i":{"x":0.833,"y":1},"s":[-10],"t":126},{"o":{"x":0.167,"y":0.167},"i":{"x":0.833,"y":0.833},"s":[-7],"t":156}],"ix":10},"sa":{"a":0,"k":0},"o":{"a":0,"k":100,"ix":11}},"ef":[],"shapes":[{"ty":"gr","bm":0,"cl":"","ln":"","hd":false,"mn":"ADBE Vector Group","nm":"Group 1","ix":1,"cix":2,"np":3,"it":[{"ty":"sh","bm":0,"cl":"","ln":"","hd":false,"mn":"ADBE Vector Shape - Group","nm":"Path 1","ix":1,"d":1,"ks":{"a":0,"k":{"c":true,"i":[[0,0],[-26.331,7.261],[0,0],[13.333,12.988]],"o":[[0,0],[0,0],[0,0],[0,0]],"v":[[-21.109,-7.692],[23.098,-4.289],[23.19,5.016],[-23.19,-5.296]]},"ix":2}},{"ty":"st","bm":0,"cl":"","ln":"","hd":false,"mn":"ADBE Vector Graphic - Stroke","nm":"Stroke 1","lc":1,"lj":2,"ml":1,"o":{"a":0,"k":100,"ix":4},"w":{"a":0,"k":1.5,"ix":5},"d":[],"c":{"a":0,"k":[0.0588,0.0902,0.1647],"ix":3}},{"ty":"fl","bm":0,"cl":"","ln":"","hd":false,"mn":"ADBE Vector Graphic - Fill","nm":"Fill 1","c":{"a":0,"k":[0.0588,0.0902,0.1647],"ix":4},"r":1,"o":{"a":0,"k":100,"ix":5}},{"ty":"tr","a":{"a":0,"k":[0,0],"ix":1},"s":{"a":0,"k":[100,100],"ix":3},"sk":{"a":0,"k":0,"ix":4},"p":{"a":0,"k":[489.624,951.992],"ix":2},"r":{"a":0,"k":0,"ix":6},"sa":{"a":0,"k":0,"ix":5},"o":{"a":0,"k":100,"ix":7}}]},{"ty":"gr","bm":0,"cl":"","ln":"","hd":false,"mn":"ADBE Vector Group","nm":"Group 2","ix":2,"cix":2,"np":2,"it":[{"ty":"sh","bm":0,"cl":"","ln":"","hd":false,"mn":"ADBE Vector Shape - Group","nm":"Path 1","ix":1,"d":1,"ks":{"a":0,"k":{"c":true,"i":[[-0.374,-0.497],[-0.36,-4.618],[-0.462,0],[-0.023,0.002],[0.038,0.493],[2.171,2.909],[0.376,0.436],[0.209,0.124],[0.251,-0.424],[-0.424,-0.252],[-2.436,-2.781]],"o":[[2.04,2.707],[0.036,0.469],[0.023,0],[0.492,-0.038],[-0.39,-5.016],[-0.371,-0.497],[-2.635,-3.056],[-0.425,-0.251],[-0.252,0.425],[0.047,0.028],[0.378,0.431]],"v":[[0.217,-2.202],[4.482,8.793],[5.372,9.618],[5.442,9.615],[6.264,8.656],[1.736,-3.216],[0.613,-4.617],[-4.826,-9.367],[-6.05,-9.055],[-5.738,-7.83],[-0.914,-3.598]]},"ix":2}},{"ty":"fl","bm":0,"cl":"","ln":"","hd":false,"mn":"ADBE Vector Graphic - Fill","nm":"Fill 1","c":{"a":0,"k":[0.0588,0.0902,0.1647],"ix":4},"r":1,"o":{"a":0,"k":100,"ix":5}},{"ty":"tr","a":{"a":0,"k":[0,0],"ix":1},"s":{"a":0,"k":[100,100],"ix":3},"sk":{"a":0,"k":0,"ix":4},"p":{"a":0,"k":[449.098,968.048],"ix":2},"r":{"a":0,"k":0,"ix":6},"sa":{"a":0,"k":0,"ix":5},"o":{"a":0,"k":100,"ix":7}}]},{"ty":"gr","bm":0,"cl":"","ln":"","hd":false,"mn":"ADBE Vector Group","nm":"Group 3","ix":3,"cix":2,"np":2,"it":[{"ty":"sh","bm":0,"cl":"","ln":"","hd":false,"mn":"ADBE Vector Shape - Group","nm":"Path 1","ix":1,"d":1,"ks":{"a":0,"k":{"c":true,"i":[[-0.386,-0.498],[0,-3.657],[-0.493,0],[0,0.493],[2.486,3.28],[0.385,0.458],[0.729,0.376],[0.224,-0.158],[-0.047,-0.331],[-0.43,-0.009],[-2.045,-2.386]],"o":[[2.382,3.074],[0,0.493],[0.494,0],[0,-4.019],[-0.377,-0.499],[-2.493,-2.973],[-0.544,-0.28],[-0.272,0.194],[0.063,0.44],[0.687,0.45],[0.389,0.453]],"v":[[0.223,-1.763],[4.774,8.812],[5.667,9.706],[6.561,8.812],[1.891,-2.562],[0.745,-3.996],[-4.985,-9.426],[-6.133,-9.417],[-6.514,-8.512],[-5.647,-7.744],[-0.943,-3.191]]},"ix":2}},{"ty":"fl","bm":0,"cl":"","ln":"","hd":false,"mn":"ADBE Vector Graphic - Fill","nm":"Fill 1","c":{"a":0,"k":[0.0588,0.0902,0.1647],"ix":4},"r":1,"o":{"a":0,"k":100,"ix":5}},{"ty":"tr","a":{"a":0,"k":[0,0],"ix":1},"s":{"a":0,"k":[100,100],"ix":3},"sk":{"a":0,"k":0,"ix":4},"p":{"a":0,"k":[433.912,976.044],"ix":2},"r":{"a":0,"k":0,"ix":6},"sa":{"a":0,"k":0,"ix":5},"o":{"a":0,"k":100,"ix":7}}]},{"ty":"gr","bm":0,"cl":"","ln":"","hd":false,"mn":"ADBE Vector Group","nm":"Group 4","ix":4,"cix":2,"np":2,"it":[{"ty":"sh","bm":0,"cl":"","ln":"","hd":false,"mn":"ADBE Vector Shape - Group","nm":"Path 1","ix":1,"d":1,"ks":{"a":0,"k":{"c":true,"i":[[-0.352,-0.523],[-0.392,-3.351],[-0.447,0],[-0.035,0.003],[0.057,0.49],[1.941,2.974],[0.357,0.494],[0.276,0.228],[0.315,-0.38],[-0.381,-0.314],[-3.271,-4.382]],"o":[[1.933,2.87],[0.053,0.455],[0.035,0],[0.49,-0.058],[-0.414,-3.537],[-0.341,-0.524],[-3.423,-4.73],[-0.38,-0.313],[-0.315,0.38],[0.063,0.053],[0.367,0.492]],"v":[[1.353,0.193],[5.304,9.717],[6.19,10.508],[6.295,10.503],[7.079,9.51],[3.112,-0.422],[2.062,-1.95],[-5.563,-10.195],[-6.821,-10.076],[-6.702,-8.818],[0.272,-1.331]]},"ix":2}},{"ty":"fl","bm":0,"cl":"","ln":"","hd":false,"mn":"ADBE Vector Graphic - Fill","nm":"Fill 1","c":{"a":0,"k":[0.0588,0.0902,0.1647],"ix":4},"r":1,"o":{"a":0,"k":100,"ix":5}},{"ty":"tr","a":{"a":0,"k":[0,0],"ix":1},"s":{"a":0,"k":[100,100],"ix":3},"sk":{"a":0,"k":0,"ix":4},"p":{"a":0,"k":[414.261,981.53],"ix":2},"r":{"a":0,"k":0,"ix":6},"sa":{"a":0,"k":0,"ix":5},"o":{"a":0,"k":100,"ix":7}}]},{"ty":"gr","bm":0,"cl":"","ln":"","hd":false,"mn":"ADBE Vector Group","nm":"Group 5","ix":5,"cix":2,"np":3,"it":[{"ty":"sh","bm":0,"cl":"","ln":"","hd":false,"mn":"ADBE Vector Shape - Group","nm":"Path 1","ix":1,"d":1,"ks":{"a":0,"k":{"c":true,"i":[[0.168,5.225],[0.317,15.277],[0,0],[6.859,-4.66],[2.418,-0.74],[0.241,-8.531],[-0.168,-0.173],[-0.241,0],[0,0],[0,0],[0,0],[-0.002,0.492]],"o":[[-0.202,-6.24],[0.005,0.24],[0,0],[-16.741,9.422],[-15.35,4.697],[-0.007,0.24],[0.169,0.173],[0,0],[0,0],[0,0],[0.492,0],[0.021,-4.636]],"v":[[62.385,20.065],[61.461,-35.816],[24.598,-35.816],[-1.292,-8.531],[-43.52,10.514],[-62.621,34.897],[-62.369,35.545],[-61.728,35.816],[-60.848,35.816],[60.815,35.816],[61.714,35.816],[62.607,34.926]]},"ix":2}},{"ty":"st","bm":0,"cl":"","ln":"","hd":false,"mn":"ADBE Vector Graphic - Stroke","nm":"Stroke 1","lc":1,"lj":1,"ml":10,"o":{"a":0,"k":100,"ix":4},"w":{"a":0,"k":1.5,"ix":5},"d":[],"c":{"a":0,"k":[0.0588,0.0902,0.1647],"ix":3}},{"ty":"fl","bm":0,"cl":"","ln":"","hd":false,"mn":"ADBE Vector Graphic - Fill","nm":"Fill 1","c":{"a":0,"k":[1,1,1],"ix":4},"r":1,"o":{"a":0,"k":100,"ix":5}},{"ty":"tr","a":{"a":0,"k":[0,0],"ix":1},"s":{"a":0,"k":[100,100],"ix":3},"sk":{"a":0,"k":0,"ix":4},"p":{"a":0,"k":[451.003,971.962],"ix":2},"r":{"a":0,"k":0,"ix":6},"sa":{"a":0,"k":0,"ix":5},"o":{"a":0,"k":100,"ix":7}}]},{"ty":"gr","bm":0,"cl":"","ln":"","hd":false,"mn":"ADBE Vector Group","nm":"Group 6","ix":6,"cix":2,"np":3,"it":[{"ty":"sh","bm":0,"cl":"","ln":"","hd":false,"mn":"ADBE Vector Shape - Group","nm":"Path 1","ix":1,"d":1,"ks":{"a":0,"k":{"c":true,"i":[[-0.007,0.24],[-0.055,-0.18],[-0.289,-0.08],[0,0],[-0.023,0.385],[-0.028,6.366]],"o":[[-0.16,5.64],[0.091,0.298],[0,0],[0.355,-0.102],[0.002,-0.035],[-0.002,0.492]],"v":[[-62.534,-5.344],[-61.357,4.751],[-60.738,5.345],[61.815,5.345],[62.462,4.544],[62.694,-5.315]]},"ix":2}},{"ty":"st","bm":0,"cl":"","ln":"","hd":false,"mn":"ADBE Vector Graphic - Stroke","nm":"Stroke 1","lc":1,"lj":2,"ml":1,"o":{"a":0,"k":100,"ix":4},"w":{"a":0,"k":1.5,"ix":5},"d":[],"c":{"a":0,"k":[0.0588,0.0902,0.1647],"ix":3}},{"ty":"fl","bm":0,"cl":"","ln":"","hd":false,"mn":"ADBE Vector Graphic - Fill","nm":"Fill 1","c":{"a":0,"k":[0.0588,0.0902,0.1647],"ix":4},"r":1,"o":{"a":0,"k":100,"ix":5}},{"ty":"tr","a":{"a":0,"k":[0,0],"ix":1},"s":{"a":0,"k":[100,100],"ix":3},"sk":{"a":0,"k":0,"ix":4},"p":{"a":0,"k":[450.915,1012.204],"ix":2},"r":{"a":0,"k":0,"ix":6},"sa":{"a":0,"k":0,"ix":5},"o":{"a":0,"k":100,"ix":7}}]}],"ind":8,"parent":7},{"ty":4,"nm":"leg R","mn":"","sr":1,"st":0,"op":180,"ip":0,"hd":false,"cl":"","ln":"","ddd":0,"bm":0,"hasMask":false,"ao":0,"ks":{"a":{"a":0,"k":[652,599,0],"ix":1},"s":{"a":0,"k":[100,100,100],"ix":6},"sk":{"a":0,"k":0},"p":{"a":0,"k":[562,369,0],"ix":2},"r":{"a":1,"k":[{"o":{"x":0.333,"y":0},"i":{"x":0.667,"y":1},"s":[0],"t":0},{"o":{"x":0.333,"y":0},"i":{"x":0.833,"y":1},"s":[3],"t":30},{"o":{"x":0.167,"y":0},"i":{"x":0.583,"y":1},"s":[6],"t":60},{"o":{"x":0.417,"y":0},"i":{"x":0.833,"y":1},"s":[5],"t":90},{"o":{"x":0.167,"y":0},"i":{"x":0.667,"y":1},"s":[6],"t":120},{"o":{"x":0.333,"y":0},"i":{"x":0.667,"y":1},"s":[3],"t":150},{"o":{"x":0.167,"y":0.167},"i":{"x":0.833,"y":0.833},"s":[0],"t":179}],"ix":10},"sa":{"a":0,"k":0},"o":{"a":0,"k":100,"ix":11}},"ef":[],"shapes":[{"ty":"gr","bm":0,"cl":"","ln":"","hd":false,"mn":"ADBE Vector Group","nm":"Group 1","ix":1,"cix":2,"np":2,"it":[{"ty":"sh","bm":0,"cl":"","ln":"","hd":false,"mn":"ADBE Vector Shape - Group","nm":"Path 1","ix":1,"d":1,"ks":{"a":0,"k":{"c":false,"i":[[0,0],[0.009,-0.016],[-22.092,-10.006],[-23.595,13.868],[4.945,21.817],[10.39,4.494],[29.737,12.393],[21.66,-4.197],[1.22,-0.373],[1.671,-1.201]],"o":[[6.13,8.58],[10.489,13.812],[24.785,15.183],[17.769,-10.446],[-4.495,-19.841],[-12.345,-6.323],[-53.914,-22.47],[-1.154,0.225],[-2.231,0.349],[0,0]],"v":[[-110.918,-21.25],[-99.487,-6.355],[-15.108,79.596],[95.969,80.974],[117.643,12.525],[70.951,-30.812],[2.355,-62.717],[-113.165,-90.644],[-116.734,-89.732],[-122.589,-87.376]]},"ix":2}},{"ty":"st","bm":0,"cl":"","ln":"","hd":false,"mn":"ADBE Vector Graphic - Stroke","nm":"Stroke 1","lc":1,"lj":1,"ml":10,"o":{"a":0,"k":100,"ix":4},"w":{"a":0,"k":1.5,"ix":5},"d":[],"c":{"a":0,"k":[0.0588,0.0902,0.1647],"ix":3}},{"ty":"tr","a":{"a":0,"k":[0,0],"ix":1},"s":{"a":0,"k":[100,100],"ix":3},"sk":{"a":0,"k":0,"ix":4},"p":{"a":0,"k":[559.532,598.31],"ix":2},"r":{"a":0,"k":0,"ix":6},"sa":{"a":0,"k":0,"ix":5},"o":{"a":0,"k":100,"ix":7}}]},{"ty":"gr","bm":0,"cl":"","ln":"","hd":false,"mn":"ADBE Vector Group","nm":"Group 2","ix":2,"cix":2,"np":2,"it":[{"ty":"sh","bm":0,"cl":"","ln":"","hd":false,"mn":"ADBE Vector Shape - Group","nm":"Path 1","ix":1,"d":1,"ks":{"a":0,"k":{"c":true,"i":[[4.944,21.816],[10.389,4.493],[29.737,12.393],[21.659,-4.198],[1.22,-0.373],[-3.911,-18.405],[0.02,-0.036],[-22.092,-10.006],[-23.595,13.868]],"o":[[-4.495,-19.842],[-12.345,-6.323],[-53.914,-22.469],[-1.155,0.224],[-11.9,1.866],[3.886,18.29],[10.49,13.812],[24.785,15.184],[17.77,-10.445]],"v":[[122.634,12.525],[75.942,-30.812],[7.345,-62.718],[-108.175,-90.643],[-111.745,-89.733],[-123.667,-54.619],[-94.497,-6.354],[-10.118,79.595],[100.959,80.973]]},"ix":2}},{"ty":"fl","bm":0,"cl":"","ln":"","hd":false,"mn":"ADBE Vector Graphic - Fill","nm":"Fill 1","c":{"a":0,"k":[1,1,1],"ix":4},"r":1,"o":{"a":0,"k":100,"ix":5}},{"ty":"tr","a":{"a":0,"k":[0,0],"ix":1},"s":{"a":0,"k":[100,100],"ix":3},"sk":{"a":0,"k":0,"ix":4},"p":{"a":0,"k":[554.542,598.31],"ix":2},"r":{"a":0,"k":0,"ix":6},"sa":{"a":0,"k":0,"ix":5},"o":{"a":0,"k":100,"ix":7}}]}],"ind":9},{"ty":4,"nm":"leg R","mn":"","sr":1,"st":0,"op":180,"ip":0,"hd":false,"cl":"","ln":"","ddd":0,"bm":0,"hasMask":false,"ao":0,"ks":{"a":{"a":0,"k":[451,538,0],"ix":1},"s":{"a":0,"k":[100,100,100],"ix":6},"sk":{"a":0,"k":0},"p":{"a":0,"k":[451,538,0],"ix":2},"r":{"a":1,"k":[{"o":{"x":0.333,"y":0},"i":{"x":0.667,"y":1},"s":[0],"t":0},{"o":{"x":0.333,"y":0},"i":{"x":0.833,"y":1},"s":[-9],"t":30},{"o":{"x":0.167,"y":0},"i":{"x":0.583,"y":1},"s":[-14],"t":60},{"o":{"x":0.417,"y":0},"i":{"x":0.833,"y":1},"s":[-12],"t":90},{"o":{"x":0.167,"y":0},"i":{"x":0.667,"y":1},"s":[-14],"t":120},{"o":{"x":0.333,"y":0},"i":{"x":0.667,"y":1},"s":[-9],"t":150},{"o":{"x":0.167,"y":0.167},"i":{"x":0.833,"y":0.833},"s":[0],"t":179}],"ix":10},"sa":{"a":0,"k":0},"o":{"a":0,"k":100,"ix":11}},"ef":[],"shapes":[{"ty":"gr","bm":0,"cl":"","ln":"","hd":false,"mn":"ADBE Vector Group","nm":"Group 1","ix":1,"cix":2,"np":3,"it":[{"ty":"sh","bm":0,"cl":"","ln":"","hd":false,"mn":"ADBE Vector Shape - Group","nm":"Path 1","ix":1,"d":1,"ks":{"a":0,"k":{"c":true,"i":[[35.075,-5.775],[38.873,-50.379],[3.445,-5.429],[-18.162,11.724],[-19.378,12.595],[-8.601,8.93]],"o":[[-21.997,3.243],[-28.863,37.404],[4.419,3.353],[16.795,-15.178],[26.006,-16.9],[41.334,-42.118]],"v":[[43.085,-91.923],[-50.521,-4.408],[-108.109,71.685],[-58.089,87.974],[-0.879,45.179],[65.025,-12.662]]},"ix":2}},{"ty":"st","bm":0,"cl":"","ln":"","hd":false,"mn":"ADBE Vector Graphic - Stroke","nm":"Stroke 1","lc":1,"lj":2,"ml":1,"o":{"a":0,"k":100,"ix":4},"w":{"a":0,"k":1.5,"ix":5},"d":[],"c":{"a":0,"k":[0.0588,0.0902,0.1647],"ix":3}},{"ty":"fl","bm":0,"cl":"","ln":"","hd":false,"mn":"ADBE Vector Graphic - Fill","nm":"Fill 1","c":{"a":0,"k":[1,1,1],"ix":4},"r":1,"o":{"a":0,"k":100,"ix":5}},{"ty":"tr","a":{"a":0,"k":[0,0],"ix":1},"s":{"a":0,"k":[100,100],"ix":3},"sk":{"a":0,"k":0,"ix":4},"p":{"a":0,"k":[402.155,599.835],"ix":2},"r":{"a":0,"k":0,"ix":6},"sa":{"a":0,"k":0,"ix":5},"o":{"a":0,"k":100,"ix":7}}]}],"ind":10,"parent":9},{"ty":4,"nm":"shoe R","mn":"","sr":1,"st":0,"op":180,"ip":0,"hd":false,"cl":"","ln":"","ddd":0,"bm":0,"hasMask":false,"ao":0,"ks":{"a":{"a":0,"k":[317.616,675.235,0],"ix":1},"s":{"a":0,"k":[100,100,100],"ix":6},"sk":{"a":0,"k":0},"p":{"a":0,"k":[317.616,675.235,0],"ix":2},"r":{"a":1,"k":[{"o":{"x":0.333,"y":0},"i":{"x":0.667,"y":1},"s":[0],"t":0},{"o":{"x":0.333,"y":0},"i":{"x":0.833,"y":1},"s":[5],"t":30},{"o":{"x":0.167,"y":0},"i":{"x":0.583,"y":1},"s":[2],"t":60},{"o":{"x":0.417,"y":0},"i":{"x":0.833,"y":1},"s":[-5],"t":90},{"o":{"x":0.167,"y":0},"i":{"x":0.667,"y":1},"s":[2],"t":120},{"o":{"x":0.333,"y":0},"i":{"x":0.667,"y":1},"s":[5],"t":150},{"o":{"x":0.167,"y":0.167},"i":{"x":0.833,"y":0.833},"s":[0],"t":179}],"ix":10},"sa":{"a":0,"k":0},"o":{"a":0,"k":100,"ix":11}},"ef":[],"shapes":[{"ty":"gr","bm":0,"cl":"","ln":"","hd":false,"mn":"ADBE Vector Group","nm":"Group 1","ix":1,"cix":2,"np":3,"it":[{"ty":"sh","bm":0,"cl":"","ln":"","hd":false,"mn":"ADBE Vector Shape - Group","nm":"Path 1","ix":1,"d":1,"ks":{"a":0,"k":{"c":true,"i":[[0,0],[-20.818,-2.144],[0,0],[6.961,19.942]],"o":[[0,0],[0,0],[0,0],[0,0]],"v":[[-16.464,-11.619],[19.16,3.96],[17.963,11.619],[-19.16,-11.014]]},"ix":2}},{"ty":"st","bm":0,"cl":"","ln":"","hd":false,"mn":"ADBE Vector Graphic - Stroke","nm":"Stroke 1","lc":1,"lj":2,"ml":1,"o":{"a":0,"k":100,"ix":4},"w":{"a":0,"k":1.5,"ix":5},"d":[],"c":{"a":0,"k":[0.0588,0.0902,0.1647],"ix":3}},{"ty":"fl","bm":0,"cl":"","ln":"","hd":false,"mn":"ADBE Vector Graphic - Fill","nm":"Fill 1","c":{"a":0,"k":[0.0588,0.0902,0.1647],"ix":4},"r":1,"o":{"a":0,"k":100,"ix":5}},{"ty":"tr","a":{"a":0,"k":[0,0],"ix":1},"s":{"a":0,"k":[100,100],"ix":3},"sk":{"a":0,"k":0,"ix":4},"p":{"a":0,"k":[311.879,685.836],"ix":2},"r":{"a":0,"k":0,"ix":6},"sa":{"a":0,"k":0,"ix":5},"o":{"a":0,"k":100,"ix":7}}]},{"ty":"gr","bm":0,"cl":"","ln":"","hd":false,"mn":"ADBE Vector Group","nm":"Group 2","ix":2,"cix":2,"np":2,"it":[{"ty":"sh","bm":0,"cl":"","ln":"","hd":false,"mn":"ADBE Vector Shape - Group","nm":"Path 1","ix":1,"d":1,"ks":{"a":0,"k":{"c":true,"i":[[-0.526,-0.556],[-0.182,-6.539],[-0.482,0],[0,0],[0.014,0.494],[2.557,2.966],[0.468,0.444],[0.052,0.021],[0.183,-0.458],[-0.457,-0.183],[-1.916,-1.598]],"o":[[2.524,2.668],[0.014,0.485],[0,0],[0.493,-0.013],[-0.18,-6.475],[-0.469,-0.543],[-2.611,-2.482],[-0.459,-0.183],[-0.184,0.458],[0.163,0.066],[0.506,0.422]],"v":[[-0.546,-4.357],[4.679,9.131],[5.572,9.999],[5.598,9.999],[6.466,9.081],[1.349,-4.835],[-0.062,-6.318],[-5.137,-9.817],[-6.296,-9.318],[-5.799,-8.157],[-2.103,-5.816]]},"ix":2}},{"ty":"fl","bm":0,"cl":"","ln":"","hd":false,"mn":"ADBE Vector Graphic - Fill","nm":"Fill 1","c":{"a":0,"k":[0.0588,0.0902,0.1647],"ix":4},"r":1,"o":{"a":0,"k":100,"ix":5}},{"ty":"tr","a":{"a":0,"k":[0,0],"ix":1},"s":{"a":0,"k":[100,100],"ix":3},"sk":{"a":0,"k":0,"ix":4},"p":{"a":0,"k":[278.807,685.498],"ix":2},"r":{"a":0,"k":0,"ix":6},"sa":{"a":0,"k":0,"ix":5},"o":{"a":0,"k":100,"ix":7}}]},{"ty":"gr","bm":0,"cl":"","ln":"","hd":false,"mn":"ADBE Vector Group","nm":"Group 3","ix":3,"cix":2,"np":2,"it":[{"ty":"sh","bm":0,"cl":"","ln":"","hd":false,"mn":"ADBE Vector Shape - Group","nm":"Path 1","ix":1,"d":1,"ks":{"a":0,"k":{"c":true,"i":[[-0.609,-0.6],[-0.374,-4.454],[-0.461,0],[-0.025,0.002],[0.041,0.493],[1.748,2.033],[0.518,0.436],[0.05,0.009],[0.086,-0.484],[-0.484,-0.087],[-1.731,-1.113]],"o":[[1.799,1.773],[0.039,0.467],[0.024,0],[0.492,-0.041],[-0.362,-4.301],[-0.496,-0.578],[-2.644,-2.225],[-0.487,-0.085],[-0.086,0.486],[0.141,0.026],[0.596,0.383]],"v":[[0.168,-2.563],[4.004,6.483],[4.895,7.302],[4.969,7.299],[5.785,6.333],[2.186,-2.962],[0.656,-4.481],[-4.707,-7.218],[-5.74,-6.495],[-5.018,-5.458],[-1.66,-4.026]]},"ix":2}},{"ty":"fl","bm":0,"cl":"","ln":"","hd":false,"mn":"ADBE Vector Graphic - Fill","nm":"Fill 1","c":{"a":0,"k":[0.0588,0.0902,0.1647],"ix":4},"r":1,"o":{"a":0,"k":100,"ix":5}},{"ty":"tr","a":{"a":0,"k":[0,0],"ix":1},"s":{"a":0,"k":[100,100],"ix":3},"sk":{"a":0,"k":0,"ix":4},"p":{"a":0,"k":[260.015,687.64],"ix":2},"r":{"a":0,"k":0,"ix":6},"sa":{"a":0,"k":0,"ix":5},"o":{"a":0,"k":100,"ix":7}}]},{"ty":"gr","bm":0,"cl":"","ln":"","hd":false,"mn":"ADBE Vector Group","nm":"Group 4","ix":4,"cix":2,"np":2,"it":[{"ty":"sh","bm":0,"cl":"","ln":"","hd":false,"mn":"ADBE Vector Shape - Group","nm":"Path 1","ix":1,"d":1,"ks":{"a":0,"k":{"c":true,"i":[[-0.494,-0.571],[0,-3.651],[-0.494,0],[0,0.494],[1.777,2.28],[0.449,0.468],[0.161,0.094],[0.25,-0.425],[-0.425,-0.251],[-1.448,-1.346]],"o":[[1.815,2.1],[0,0.494],[0.493,0],[0,-3.772],[-0.441,-0.567],[-1.923,-2],[-0.425,-0.253],[-0.252,0.425],[0.03,0.018],[0.475,0.442]],"v":[[-0.304,-2.096],[3.234,6.608],[4.129,7.503],[5.023,6.608],[1.702,-2.508],[0.357,-4.059],[-3.548,-7.25],[-4.77,-6.935],[-4.456,-5.711],[-1.772,-3.616]]},"ix":2}},{"ty":"fl","bm":0,"cl":"","ln":"","hd":false,"mn":"ADBE Vector Graphic - Fill","nm":"Fill 1","c":{"a":0,"k":[0.0588,0.0902,0.1647],"ix":4},"r":1,"o":{"a":0,"k":100,"ix":5}},{"ty":"tr","a":{"a":0,"k":[0,0],"ix":1},"s":{"a":0,"k":[100,100],"ix":3},"sk":{"a":0,"k":0,"ix":4},"p":{"a":0,"k":[237.504,691.632],"ix":2},"r":{"a":0,"k":0,"ix":6},"sa":{"a":0,"k":0,"ix":5},"o":{"a":0,"k":100,"ix":7}}]},{"ty":"gr","bm":0,"cl":"","ln":"","hd":false,"mn":"ADBE Vector Group","nm":"Group 5","ix":5,"cix":2,"np":3,"it":[{"ty":"sh","bm":0,"cl":"","ln":"","hd":false,"mn":"ADBE Vector Shape - Group","nm":"Path 1","ix":1,"d":1,"ks":{"a":0,"k":{"c":true,"i":[[0.17,0.206],[0.266,0],[0,0],[0,0],[0,0],[0.072,-0.432],[-0.086,-1.897],[-0.004,-0.053],[-0.464,0],[0,0],[-0.124,0.36],[-0.232,0.745],[-1.038,5.336]],"o":[[-0.17,-0.206],[0,0],[0,0],[0,0],[-0.437,0],[-0.9,5.438],[0.026,0.571],[0.04,0.462],[0,0],[0.381,0],[0.005,-0.015],[0.608,-1.952],[0.051,-0.261]],"v":[[63.42,-6.856],[62.731,-7.181],[61.991,-7.181],[-60.813,-7.181],[-61.877,-7.181],[-62.759,-6.433],[-63.512,5.394],[-63.453,6.365],[-62.562,7.181],[59.509,7.181],[60.354,6.579],[60.735,5.394],[63.608,-6.117]]},"ix":2}},{"ty":"st","bm":0,"cl":"","ln":"","hd":false,"mn":"ADBE Vector Graphic - Stroke","nm":"Stroke 1","lc":1,"lj":2,"ml":1,"o":{"a":0,"k":100,"ix":4},"w":{"a":0,"k":1.5,"ix":5},"d":[],"c":{"a":0,"k":[0.0588,0.0902,0.1647],"ix":3}},{"ty":"fl","bm":0,"cl":"","ln":"","hd":false,"mn":"ADBE Vector Graphic - Fill","nm":"Fill 1","c":{"a":0,"k":[0.0588,0.0902,0.1647],"ix":4},"r":1,"o":{"a":0,"k":100,"ix":5}},{"ty":"tr","a":{"a":0,"k":[0,0],"ix":1},"s":{"a":0,"k":[100,100],"ix":3},"sk":{"a":0,"k":0,"ix":4},"p":{"a":0,"k":[264.015,726.171],"ix":2},"r":{"a":0,"k":0,"ix":6},"sa":{"a":0,"k":0,"ix":5},"o":{"a":0,"k":100,"ix":7}}]},{"ty":"gr","bm":0,"cl":"","ln":"","hd":false,"mn":"ADBE Vector Group","nm":"Group 6","ix":6,"cix":2,"np":3,"it":[{"ty":"sh","bm":0,"cl":"","ln":"","hd":false,"mn":"ADBE Vector Shape - Group","nm":"Path 1","ix":1,"d":1,"ks":{"a":0,"k":{"c":true,"i":[[-0.959,2.618],[-0.203,0.218],[0.034,0.026],[3.528,-1.079],[1.74,-10.514],[0.05,-0.261],[0.191,5.896]],"o":[[-0.148,0.405],[-0.037,-0.027],[-5.07,1.854],[-15.22,4.659],[0.071,-0.432],[1.362,-7.008],[-0.043,-1.351]],"v":[[65.76,-16.226],[37.802,-23.896],[27.927,-21.823],[-43.532,-5.076],[-65.76,23.607],[60.607,23.922],[62.373,4.476]]},"ix":2}},{"ty":"st","bm":0,"cl":"","ln":"","hd":false,"mn":"ADBE Vector Graphic - Stroke","nm":"Stroke 1","lc":1,"lj":2,"ml":1,"o":{"a":0,"k":100,"ix":4},"w":{"a":0,"k":1.5,"ix":5},"d":[],"c":{"a":0,"k":[0.0588,0.0902,0.1647],"ix":3}},{"ty":"fl","bm":0,"cl":"","ln":"","hd":false,"mn":"ADBE Vector Graphic - Fill","nm":"Fill 1","c":{"a":0,"k":[1,1,1],"ix":4},"r":1,"o":{"a":0,"k":100,"ix":5}},{"ty":"tr","a":{"a":0,"k":[0,0],"ix":1},"s":{"a":0,"k":[100,100],"ix":3},"sk":{"a":0,"k":0,"ix":4},"p":{"a":0,"k":[267.016,696.131],"ix":2},"r":{"a":0,"k":0,"ix":6},"sa":{"a":0,"k":0,"ix":5},"o":{"a":0,"k":100,"ix":7}}]}],"ind":11,"parent":10},{"ty":4,"nm":"hair","mn":"","sr":1,"st":0,"op":180,"ip":0,"hd":false,"cl":"","ln":"","ddd":0,"bm":0,"hasMask":false,"ao":0,"ks":{"a":{"a":0,"k":[654.47,331.362,0],"ix":1},"s":{"a":0,"k":[100,100,100],"ix":6},"sk":{"a":0,"k":0},"p":{"a":0,"k":[654.47,331.362,0],"ix":2},"r":{"a":0,"k":0,"ix":10},"sa":{"a":0,"k":0},"o":{"a":0,"k":100,"ix":11}},"ef":[],"shapes":[{"ty":"gr","bm":0,"cl":"","ln":"","hd":false,"mn":"ADBE Vector Group","nm":"Group 1","ix":1,"cix":2,"np":3,"it":[{"ty":"sh","bm":0,"cl":"","ln":"","hd":false,"mn":"ADBE Vector Shape - Group","nm":"Path 1","ix":1,"d":1,"ks":{"a":0,"k":{"c":true,"i":[[0.189,0.686],[-1.394,-16.549],[-0.423,-0.355],[-0.145,-0.029],[-3.994,0],[-3.254,0.767],[-0.101,0.655]],"o":[[-7.173,8.773],[1.978,23.487],[0.114,0.094],[0.299,0.062],[2.612,0],[6.229,-1.608],[0.16,-1.05]],"v":[[1.277,-41.602],[-20.084,8.364],[-7.701,40.797],[-7.307,40.986],[-0.204,41.602],[8.781,40.595],[21.319,36.184]]},"ix":2}},{"ty":"st","bm":0,"cl":"","ln":"","hd":false,"mn":"ADBE Vector Graphic - Stroke","nm":"Stroke 1","lc":1,"lj":1,"ml":10,"o":{"a":0,"k":100,"ix":4},"w":{"a":0,"k":1.5,"ix":5},"d":[],"c":{"a":0,"k":[0.0588,0.0902,0.1647],"ix":3}},{"ty":"fl","bm":0,"cl":"","ln":"","hd":false,"mn":"ADBE Vector Graphic - Fill","nm":"Fill 1","c":{"a":0,"k":[0.0588,0.0902,0.1647],"ix":4},"r":1,"o":{"a":0,"k":100,"ix":5}},{"ty":"tr","a":{"a":0,"k":[0,0],"ix":1},"s":{"a":0,"k":[100,100],"ix":3},"sk":{"a":0,"k":0,"ix":4},"p":{"a":0,"k":[653.896,372.963],"ix":2},"r":{"a":0,"k":0,"ix":6},"sa":{"a":0,"k":0,"ix":5},"o":{"a":0,"k":100,"ix":7}}]}],"ind":12,"parent":1},{"ty":4,"nm":"arm R","mn":"","sr":1,"st":0,"op":180,"ip":0,"hd":false,"cl":"","ln":"","ddd":0,"bm":0,"hasMask":false,"ao":0,"ks":{"a":{"a":0,"k":[641.036,452.815,0],"ix":1},"s":{"a":0,"k":[100,100,100],"ix":6},"sk":{"a":0,"k":0},"p":{"a":0,"k":[641.036,452.815,0],"ix":2},"r":{"a":1,"k":[{"o":{"x":0.333,"y":0},"i":{"x":0.667,"y":1},"s":[-56],"t":15},{"o":{"x":0.167,"y":0},"i":{"x":0.833,"y":1},"s":[-10],"t":45},{"o":{"x":0.167,"y":0},"i":{"x":0.667,"y":1},"s":[9],"t":63},{"o":{"x":0.167,"y":0},"i":{"x":0.621,"y":1.31},"s":[-10],"t":90},{"o":{"x":0.215,"y":0.052},"i":{"x":0.837,"y":1},"s":[-26.735],"t":120},{"o":{"x":0.167,"y":0},"i":{"x":0.833,"y":1},"s":[9],"t":139},{"o":{"x":0.167,"y":0.167},"i":{"x":0.833,"y":0.833},"s":[-56],"t":169}],"ix":10},"sa":{"a":0,"k":0},"o":{"a":0,"k":100,"ix":11}},"ef":[],"shapes":[{"ty":"gr","bm":0,"cl":"","ln":"","hd":false,"mn":"ADBE Vector Group","nm":"Group 1","ix":1,"cix":2,"np":2,"it":[{"ty":"sh","bm":0,"cl":"","ln":"","hd":false,"mn":"ADBE Vector Shape - Group","nm":"Path 1","ix":1,"d":1,"ks":{"a":0,"k":{"c":true,"i":[[18.436,12.501],[19.904,-6.477],[-32.748,4.543],[-50.557,26.83]],"o":[[-12.416,-8.419],[-28.073,9.136],[34.869,-4.836],[1.391,-0.738]],"v":[[57.684,-36.465],[-48.047,-2.232],[-42.462,40.341],[62.447,0.122]]},"ix":2}},{"ty":"fl","bm":0,"cl":"","ln":"","hd":false,"mn":"ADBE Vector Graphic - Fill","nm":"Fill 1","c":{"a":0,"k":[0.0588,0.0902,0.1647],"ix":4},"r":1,"o":{"a":0,"k":100,"ix":5}},{"ty":"tr","a":{"a":0,"k":[0,0],"ix":1},"s":{"a":0,"k":[100,100],"ix":3},"sk":{"a":0,"k":0,"ix":4},"p":{"a":0,"k":[586.73,474.321],"ix":2},"r":{"a":0,"k":0,"ix":6},"sa":{"a":0,"k":0,"ix":5},"o":{"a":0,"k":100,"ix":7}}]}],"ind":13,"parent":5},{"ty":4,"nm":"arm R","mn":"","sr":1,"st":0,"op":180,"ip":0,"hd":false,"cl":"","ln":"","ddd":0,"bm":0,"hasMask":false,"ao":0,"ks":{"a":{"a":0,"k":[539.997,495.514,0],"ix":1},"s":{"a":0,"k":[100,100,100],"ix":6},"sk":{"a":0,"k":0},"p":{"a":0,"k":[539.997,495.514,0],"ix":2},"r":{"a":1,"k":[{"o":{"x":0.333,"y":0},"i":{"x":0.667,"y":1},"s":[-32],"t":15},{"o":{"x":0.167,"y":0},"i":{"x":0.833,"y":1},"s":[38],"t":45},{"o":{"x":0.167,"y":0},"i":{"x":0.667,"y":1},"s":[-23],"t":63},{"o":{"x":0.167,"y":0},"i":{"x":0.621,"y":0.741},"s":[22],"t":90},{"o":{"x":0.215,"y":0.034},"i":{"x":0.837,"y":1},"s":[9.839],"t":120},{"o":{"x":0.167,"y":0},"i":{"x":0.833,"y":1},"s":[-23],"t":139},{"o":{"x":0.167,"y":0.167},"i":{"x":0.833,"y":0.833},"s":[-32],"t":169}],"ix":10},"sa":{"a":0,"k":0},"o":{"a":0,"k":100,"ix":11}},"ef":[],"shapes":[{"ty":"gr","bm":0,"cl":"","ln":"","hd":false,"mn":"ADBE Vector Group","nm":"Group 1","ix":1,"cix":2,"np":2,"it":[{"ty":"sh","bm":0,"cl":"","ln":"","hd":false,"mn":"ADBE Vector Shape - Group","nm":"Path 1","ix":1,"d":1,"ks":{"a":0,"k":{"c":true,"i":[[16.254,20.7],[0.264,0.22],[1.638,-9.976],[-21.267,-21.498],[-7.772,-2.562],[-5.225,5.601]],"o":[[-9.427,-12.005],[-7.991,-6.646],[-0.682,4.149],[6.793,6.867],[11.373,3.749],[6.012,-6.446]],"v":[[41.208,20.981],[-27.382,-62.216],[-57.779,-48.929],[3.605,48.45],[26.555,64.613],[48.081,59.332]]},"ix":2}},{"ty":"fl","bm":0,"cl":"","ln":"","hd":false,"mn":"ADBE Vector Graphic - Fill","nm":"Fill 1","c":{"a":0,"k":[0.0588,0.0902,0.1647],"ix":4},"r":1,"o":{"a":0,"k":100,"ix":5}},{"ty":"tr","a":{"a":0,"k":[0,0],"ix":1},"s":{"a":0,"k":[100,100],"ix":3},"sk":{"a":0,"k":0,"ix":4},"p":{"a":0,"k":[503.868,449.106],"ix":2},"r":{"a":0,"k":0,"ix":6},"sa":{"a":0,"k":0,"ix":5},"o":{"a":0,"k":100,"ix":7}}]}],"ind":14,"parent":13},{"ty":4,"nm":"arm R","mn":"","sr":1,"st":0,"op":180,"ip":0,"hd":false,"cl":"","ln":"","ddd":0,"bm":0,"hasMask":false,"ao":0,"ks":{"a":{"a":0,"k":[460.031,392.224,0],"ix":1},"s":{"a":0,"k":[100.744,100.744,100],"ix":6},"sk":{"a":0,"k":0},"p":{"a":0,"k":[459.954,393.979,0],"ix":2},"r":{"a":1,"k":[{"o":{"x":0.333,"y":0},"i":{"x":0.667,"y":1},"s":[-15],"t":15},{"o":{"x":0.167,"y":0},"i":{"x":0.833,"y":1},"s":[15],"t":45},{"o":{"x":0.167,"y":0},"i":{"x":0.667,"y":1},"s":[-11],"t":63},{"o":{"x":0.167,"y":0},"i":{"x":0.833,"y":1},"s":[8],"t":90},{"o":{"x":0.167,"y":0},"i":{"x":0.833,"y":1},"s":[-11],"t":120},{"o":{"x":0.167,"y":0},"i":{"x":0.833,"y":1},"s":[-11],"t":139},{"o":{"x":0.167,"y":0.167},"i":{"x":0.833,"y":0.833},"s":[-15],"t":169}],"ix":10},"sa":{"a":0,"k":0},"o":{"a":0,"k":100,"ix":11}},"ef":[],"shapes":[{"ty":"gr","bm":0,"cl":"","ln":"","hd":false,"mn":"ADBE Vector Group","nm":"Group 2","ix":1,"cix":2,"np":3,"it":[{"ty":"sh","bm":0,"cl":"","ln":"","hd":false,"mn":"ADBE Vector Shape - Group","nm":"Path 1","ix":1,"d":1,"ks":{"a":0,"k":{"c":true,"i":[[0.847,-2.251],[-1.603,-2.462],[-0.401,-0.503],[-3.143,-2.295],[-0.49,-0.399],[1.954,0.227],[0.273,-1.496],[-0.919,-0.711],[-1.792,-1.203],[-4.957,-4.554],[1.445,13.778],[5.624,4.924],[0.97,0.601],[0.735,0.369],[5.436,-1.364]],"o":[[-0.933,2.478],[0.334,0.514],[3.008,3.771],[0.825,0.602],[-0.631,0.291],[-2.768,-0.321],[-0.085,0.47],[0.774,0.599],[4.297,2.884],[2.864,1.064],[-3.091,-8.602],[-0.773,-0.677],[-0.663,-0.411],[-6.249,-3.149],[-2.976,0.746]],"v":[[-23.383,-20.363],[-21.958,-12.855],[-20.855,-11.329],[-9.658,-2.017],[-3.512,1.699],[-10.493,0.667],[-15.732,3.686],[-14.807,5.576],[-10.826,8.327],[5.411,20.452],[22.871,12.53],[7.379,-18.484],[4.747,-20.403],[2.647,-21.575],[-17.539,-24.944]]},"ix":2}},{"ty":"st","bm":0,"cl":"","ln":"","hd":false,"mn":"ADBE Vector Graphic - Stroke","nm":"Stroke 1","lc":2,"lj":2,"ml":1,"o":{"a":0,"k":100,"ix":4},"w":{"a":0,"k":2,"ix":5},"d":[],"c":{"a":0,"k":[0.0588,0.0902,0.1647],"ix":3}},{"ty":"fl","bm":0,"cl":"","ln":"","hd":false,"mn":"ADBE Vector Graphic - Fill","nm":"Fill 1","c":{"a":0,"k":[1,1,1],"ix":4},"r":1,"o":{"a":0,"k":100,"ix":5}},{"ty":"tr","a":{"a":0,"k":[0,0],"ix":1},"s":{"a":0,"k":[100,100],"ix":3},"sk":{"a":0,"k":0,"ix":4},"p":{"a":0,"k":[446.254,374.422],"ix":2},"r":{"a":0,"k":0,"ix":6},"sa":{"a":0,"k":0,"ix":5},"o":{"a":0,"k":100,"ix":7}}]}],"ind":15,"parent":14}],"id":"comp_0"},{"nm":"","mn":"","layers":[{"ty":4,"nm":"tree","mn":"","sr":1,"st":0,"op":180,"ip":0,"hd":false,"cl":"","ln":"","ddd":0,"bm":0,"hasMask":false,"ao":0,"ks":{"a":{"a":0,"k":[839.152,1019.489,0],"ix":1},"s":{"a":0,"k":[100,100,100],"ix":6},"sk":{"a":0,"k":0},"p":{"a":0,"k":[839.152,1019.489,0],"ix":2},"r":{"a":0,"k":0,"ix":10},"sa":{"a":0,"k":0},"o":{"a":0,"k":100,"ix":11}},"ef":[],"shapes":[{"ty":"gr","bm":0,"cl":"","ln":"","hd":false,"mn":"ADBE Vector Group","nm":"Group 19","ix":1,"cix":2,"np":3,"it":[{"ty":"gr","bm":0,"cl":"","ln":"","hd":false,"mn":"ADBE Vector Group","nm":"Group 1","ix":1,"cix":2,"np":3,"it":[{"ty":"sh","bm":0,"cl":"","ln":"","hd":false,"mn":"ADBE Vector Shape - Group","nm":"Path 1","ix":1,"d":1,"ks":{"a":0,"k":{"c":true,"i":[[0.005,0.336],[8.138,0],[0,0],[0,0],[0,0],[0,0],[0,0],[0,0],[0,0],[0,0],[0,0],[0,0],[0,0],[0,0],[0,0],[0,0],[0,0],[0,0],[0,0],[3.099,-6.389],[0,-7.898],[-11.727,0],[0,0],[0,0],[0,0],[0,0],[0,0],[0.065,15.198]],"o":[[-0.227,-14.844],[0,0],[0,0],[0,0],[0,0],[0,0],[0,0],[0,0],[0,0],[0,0],[0,0],[0,0],[0,0],[0,0],[0,0],[0,0],[0,0],[0,0],[-5.362,0],[-2.665,5.495],[0,14.707],[0,0],[0,0],[0,0],[0,0],[0,0],[8.346,-0.036],[-0.002,-0.336]],"v":[[95.083,-1.059],[82.914,-30.536],[82.885,-30.536],[79.922,-30.536],[77.859,-30.536],[66.457,-30.536],[64.658,-30.536],[9.788,-30.536],[7.994,-30.536],[-1.937,-30.536],[-3.723,-30.536],[-22.478,-30.536],[-24.265,-30.536],[-40.828,-30.536],[-42.962,-30.536],[-42.967,-30.536],[-55.291,-30.536],[-58.096,-30.536],[-78.092,-30.536],[-91.027,-20.769],[-95.16,0],[-78.092,30.535],[-71.381,30.535],[-69.532,30.535],[74.26,30.535],[76.109,30.535],[83.145,30.535],[95.095,-0.052]]},"ix":2}},{"ty":"st","bm":0,"cl":"","ln":"","hd":false,"mn":"ADBE Vector Graphic - Stroke","nm":"Stroke 1","lc":1,"lj":2,"ml":1,"o":{"a":0,"k":100,"ix":4},"w":{"a":0,"k":1.5,"ix":5},"d":[],"c":{"a":0,"k":[0.0588,0.0902,0.1647],"ix":3}},{"ty":"fl","bm":0,"cl":"","ln":"","hd":false,"mn":"ADBE Vector Graphic - Fill","nm":"Fill 1","c":{"a":0,"k":[1,1,1],"ix":4},"r":1,"o":{"a":0,"k":100,"ix":5}},{"ty":"tr","a":{"a":0,"k":[0,0],"ix":1},"s":{"a":0,"k":[100,100],"ix":3},"sk":{"a":0,"k":0,"ix":4},"p":{"a":0,"k":[800.343,974.848],"ix":2},"r":{"a":0,"k":0,"ix":6},"sa":{"a":0,"k":0,"ix":5},"o":{"a":0,"k":100,"ix":7}}]},{"ty":"gr","bm":0,"cl":"","ln":"","hd":false,"mn":"ADBE Vector Group","nm":"Group 2","ix":2,"cix":2,"np":3,"it":[{"ty":"sh","bm":0,"cl":"","ln":"","hd":false,"mn":"ADBE Vector Shape - Group","nm":"Path 1","ix":1,"d":1,"ks":{"a":0,"k":{"c":true,"i":[[0.043,0.312],[0.551,2.359],[0.415,0],[0,0],[0,0],[0,0],[0.094,-0.404],[0.322,-2.361],[0.038,-0.311],[-0.17,-0.192],[-0.065,-0.042],[-0.178,0],[0,0],[-0.145,0.098],[-0.052,0.058],[0.031,0.254]],"o":[[-0.322,-2.361],[-0.093,-0.404],[0,0],[0,0],[0,0],[-0.416,0],[-0.55,2.359],[-0.043,0.312],[-0.031,0.254],[0.052,0.058],[0.144,0.098],[0,0],[0.179,0],[0.064,-0.042],[0.17,-0.192],[-0.039,-0.311]],"v":[[76.437,2.928],[75.13,-4.176],[74.26,-4.867],[73.125,-4.867],[-73.125,-4.867],[-74.26,-4.867],[-75.13,-4.176],[-76.437,2.928],[-76.565,3.865],[-76.347,4.567],[-76.172,4.715],[-75.679,4.867],[75.677,4.867],[76.172,4.715],[76.347,4.567],[76.565,3.865]]},"ix":2}},{"ty":"st","bm":0,"cl":"","ln":"","hd":false,"mn":"ADBE Vector Graphic - Stroke","nm":"Stroke 1","lc":1,"lj":2,"ml":1,"o":{"a":0,"k":100,"ix":4},"w":{"a":0,"k":1.5,"ix":5},"d":[],"c":{"a":0,"k":[0.0588,0.0902,0.1647],"ix":3}},{"ty":"fl","bm":0,"cl":"","ln":"","hd":false,"mn":"ADBE Vector Graphic - Fill","nm":"Fill 1","c":{"a":0,"k":[1,1,1],"ix":4},"r":1,"o":{"a":0,"k":100,"ix":5}},{"ty":"tr","a":{"a":0,"k":[0,0],"ix":1},"s":{"a":0,"k":[100,100],"ix":3},"sk":{"a":0,"k":0,"ix":4},"p":{"a":0,"k":[802.707,1014.621],"ix":2},"r":{"a":0,"k":0,"ix":6},"sa":{"a":0,"k":0,"ix":5},"o":{"a":0,"k":100,"ix":7}}]},{"ty":"gr","bm":0,"cl":"","ln":"","hd":false,"mn":"ADBE Vector Group","nm":"Group 3","ix":3,"cix":2,"np":3,"it":[{"ty":"sh","bm":0,"cl":"","ln":"","hd":false,"mn":"ADBE Vector Shape - Group","nm":"Path 1","ix":1,"d":1,"ks":{"a":0,"k":{"c":true,"i":[[0.515,1.671],[0,0],[0,0],[0,0],[0.398,-1.707],[-0.094,-0.404]],"o":[[0,0],[0,0],[0,0],[-0.515,1.671],[0.095,-0.404],[-0.398,-1.707]],"v":[[73.746,-2.531],[71.896,-2.531],[-71.896,-2.531],[-73.745,-2.531],[-75.13,2.531],[75.13,2.531]]},"ix":2}},{"ty":"st","bm":0,"cl":"","ln":"","hd":false,"mn":"ADBE Vector Graphic - Stroke","nm":"Stroke 1","lc":1,"lj":2,"ml":1,"o":{"a":0,"k":100,"ix":4},"w":{"a":0,"k":1.5,"ix":5},"d":[],"c":{"a":0,"k":[0.0588,0.0902,0.1647],"ix":3}},{"ty":"fl","bm":0,"cl":"","ln":"","hd":false,"mn":"ADBE Vector Graphic - Fill","nm":"Fill 1","c":{"a":0,"k":[0.0588,0.0902,0.1647],"ix":4},"r":1,"o":{"a":0,"k":100,"ix":5}},{"ty":"tr","a":{"a":0,"k":[0,0],"ix":1},"s":{"a":0,"k":[100,100],"ix":3},"sk":{"a":0,"k":0,"ix":4},"p":{"a":0,"k":[802.707,1007.914],"ix":2},"r":{"a":0,"k":0,"ix":6},"sa":{"a":0,"k":0,"ix":5},"o":{"a":0,"k":100,"ix":7}}]},{"ty":"tr","a":{"a":0,"k":[800.311,981.9],"ix":1},"s":{"a":0,"k":[100,100],"ix":3},"sk":{"a":0,"k":0,"ix":4},"p":{"a":0,"k":[800.311,981.9],"ix":2},"r":{"a":0,"k":0,"ix":6},"sa":{"a":0,"k":0,"ix":5},"o":{"a":0,"k":100,"ix":7}}]},{"ty":"gr","bm":0,"cl":"","ln":"","hd":false,"mn":"ADBE Vector Group","nm":"Group 20","ix":2,"cix":2,"np":3,"it":[{"ty":"gr","bm":0,"cl":"","ln":"","hd":false,"mn":"ADBE Vector Group","nm":"Group 4","ix":1,"cix":2,"np":2,"it":[{"ty":"sh","bm":0,"cl":"","ln":"","hd":false,"mn":"ADBE Vector Shape - Group","nm":"Path 1","ix":1,"d":1,"ks":{"a":0,"k":{"c":false,"i":[[0,0],[43.609,-55]],"o":[[0,0],[0,0]],"v":[[26.281,-80.278],[-26.282,80.278]]},"ix":2}},{"ty":"st","bm":0,"cl":"","ln":"","hd":false,"mn":"ADBE Vector Graphic - Stroke","nm":"Stroke 1","lc":1,"lj":2,"ml":1,"o":{"a":0,"k":100,"ix":4},"w":{"a":0,"k":1.5,"ix":5},"d":[],"c":{"a":0,"k":[0.0588,0.0902,0.1647],"ix":3}},{"ty":"tr","a":{"a":0,"k":[0,0],"ix":1},"s":{"a":0,"k":[100,100],"ix":3},"sk":{"a":0,"k":0,"ix":4},"p":{"a":0,"k":[812.161,909.971],"ix":2},"r":{"a":0,"k":0,"ix":6},"sa":{"a":0,"k":0,"ix":5},"o":{"a":0,"k":100,"ix":7}}]},{"ty":"gr","bm":0,"cl":"","ln":"","hd":false,"mn":"ADBE Vector Group","nm":"Group 5","ix":2,"cix":2,"np":3,"it":[{"ty":"sh","bm":0,"cl":"","ln":"","hd":false,"mn":"ADBE Vector Shape - Group","nm":"Path 1","ix":1,"d":1,"ks":{"a":0,"k":{"c":true,"i":[[-42.482,51.454],[11.729,-25.512]],"o":[[0,0],[0,0]],"v":[[21.241,-47.729],[2.12,47.729]]},"ix":2}},{"ty":"st","bm":0,"cl":"","ln":"","hd":false,"mn":"ADBE Vector Graphic - Stroke","nm":"Stroke 1","lc":1,"lj":2,"ml":1,"o":{"a":0,"k":100,"ix":4},"w":{"a":0,"k":1.5,"ix":5},"d":[],"c":{"a":0,"k":[0.0588,0.0902,0.1647],"ix":3}},{"ty":"fl","bm":0,"cl":"","ln":"","hd":false,"mn":"ADBE Vector Graphic - Fill","nm":"Fill 1","c":{"a":0,"k":[0.0588,0.0902,0.1647],"ix":4},"r":1,"o":{"a":0,"k":100,"ix":5}},{"ty":"tr","a":{"a":0,"k":[0,0],"ix":1},"s":{"a":0,"k":[100,100],"ix":3},"sk":{"a":0,"k":0,"ix":4},"p":{"a":0,"k":[816.69,876.212],"ix":2},"r":{"a":0,"k":0,"ix":6},"sa":{"a":0,"k":0,"ix":5},"o":{"a":0,"k":100,"ix":7}}]},{"ty":"gr","bm":0,"cl":"","ln":"","hd":false,"mn":"ADBE Vector Group","nm":"Group 6","ix":3,"cix":2,"np":3,"it":[{"ty":"sh","bm":0,"cl":"","ln":"","hd":false,"mn":"ADBE Vector Shape - Group","nm":"Path 1","ix":1,"d":1,"ks":{"a":0,"k":{"c":true,"i":[[-42.482,51.454],[45.233,-38.18]],"o":[[0,0],[0,0]],"v":[[8.185,-47.729],[-10.936,47.729]]},"ix":2}},{"ty":"st","bm":0,"cl":"","ln":"","hd":false,"mn":"ADBE Vector Graphic - Stroke","nm":"Stroke 1","lc":1,"lj":2,"ml":1,"o":{"a":0,"k":100,"ix":4},"w":{"a":0,"k":1.5,"ix":5},"d":[],"c":{"a":0,"k":[0.0588,0.0902,0.1647],"ix":3}},{"ty":"fl","bm":0,"cl":"","ln":"","hd":false,"mn":"ADBE Vector Graphic - Fill","nm":"Fill 1","c":{"a":0,"k":[1,1,1],"ix":4},"r":1,"o":{"a":0,"k":100,"ix":5}},{"ty":"tr","a":{"a":0,"k":[0,0],"ix":1},"s":{"a":0,"k":[100,100],"ix":3},"sk":{"a":0,"k":0,"ix":4},"p":{"a":0,"k":[829.746,876.212],"ix":2},"r":{"a":0,"k":0,"ix":6},"sa":{"a":0,"k":0,"ix":5},"o":{"a":0,"k":100,"ix":7}}]},{"ty":"tr","a":{"a":0,"k":[784.654,990.366],"ix":1},"s":{"a":0,"k":[100,100],"ix":3},"sk":{"a":0,"k":0,"ix":4},"p":{"a":0,"k":[784.654,990.366],"ix":2},"r":{"a":1,"k":[{"o":{"x":0.333,"y":0},"i":{"x":0.667,"y":1},"s":[0],"t":0},{"o":{"x":0.333,"y":0},"i":{"x":0.667,"y":1},"s":[4],"t":90},{"o":{"x":0.167,"y":0.167},"i":{"x":0.833,"y":0.833},"s":[0],"t":179}],"ix":6},"sa":{"a":0,"k":0,"ix":5},"o":{"a":0,"k":100,"ix":7}}]},{"ty":"gr","bm":0,"cl":"","ln":"","hd":false,"mn":"ADBE Vector Group","nm":"Group 21","ix":3,"cix":2,"np":3,"it":[{"ty":"gr","bm":0,"cl":"","ln":"","hd":false,"mn":"ADBE Vector Group","nm":"Group 7","ix":1,"cix":2,"np":2,"it":[{"ty":"sh","bm":0,"cl":"","ln":"","hd":false,"mn":"ADBE Vector Shape - Group","nm":"Path 1","ix":1,"d":1,"ks":{"a":0,"k":{"c":false,"i":[[0,0],[-52.236,-65.881]],"o":[[0,0],[0,0]],"v":[[-31.481,-96.161],[31.481,96.16]]},"ix":2}},{"ty":"st","bm":0,"cl":"","ln":"","hd":false,"mn":"ADBE Vector Graphic - Stroke","nm":"Stroke 1","lc":1,"lj":2,"ml":1,"o":{"a":0,"k":100,"ix":4},"w":{"a":0,"k":1.5,"ix":5},"d":[],"c":{"a":0,"k":[0.0588,0.0902,0.1647],"ix":3}},{"ty":"tr","a":{"a":0,"k":[0,0],"ix":1},"s":{"a":0,"k":[100,100],"ix":3},"sk":{"a":0,"k":0,"ix":4},"p":{"a":0,"k":[805.245,862.156],"ix":2},"r":{"a":0,"k":0,"ix":6},"sa":{"a":0,"k":0,"ix":5},"o":{"a":0,"k":100,"ix":7}}]},{"ty":"gr","bm":0,"cl":"","ln":"","hd":false,"mn":"ADBE Vector Group","nm":"Group 8","ix":2,"cix":2,"np":3,"it":[{"ty":"sh","bm":0,"cl":"","ln":"","hd":false,"mn":"ADBE Vector Shape - Group","nm":"Path 1","ix":1,"d":1,"ks":{"a":0,"k":{"c":true,"i":[[50.887,61.634],[-14.049,-30.559]],"o":[[0,0],[0,0]],"v":[[-25.443,-57.172],[-2.541,57.172]]},"ix":2}},{"ty":"st","bm":0,"cl":"","ln":"","hd":false,"mn":"ADBE Vector Graphic - Stroke","nm":"Stroke 1","lc":1,"lj":2,"ml":1,"o":{"a":0,"k":100,"ix":4},"w":{"a":0,"k":1.5,"ix":5},"d":[],"c":{"a":0,"k":[0.0588,0.0902,0.1647],"ix":3}},{"ty":"fl","bm":0,"cl":"","ln":"","hd":false,"mn":"ADBE Vector Graphic - Fill","nm":"Fill 1","c":{"a":0,"k":[0.0588,0.0902,0.1647],"ix":4},"r":1,"o":{"a":0,"k":100,"ix":5}},{"ty":"tr","a":{"a":0,"k":[0,0],"ix":1},"s":{"a":0,"k":[100,100],"ix":3},"sk":{"a":0,"k":0,"ix":4},"p":{"a":0,"k":[799.82,821.718],"ix":2},"r":{"a":0,"k":0,"ix":6},"sa":{"a":0,"k":0,"ix":5},"o":{"a":0,"k":100,"ix":7}}]},{"ty":"gr","bm":0,"cl":"","ln":"","hd":false,"mn":"ADBE Vector Group","nm":"Group 9","ix":3,"cix":2,"np":3,"it":[{"ty":"sh","bm":0,"cl":"","ln":"","hd":false,"mn":"ADBE Vector Shape - Group","nm":"Path 1","ix":1,"d":1,"ks":{"a":0,"k":{"c":true,"i":[[50.887,61.634],[-54.182,-45.734]],"o":[[0,0],[0,0]],"v":[[-9.804,-57.172],[13.099,57.172]]},"ix":2}},{"ty":"st","bm":0,"cl":"","ln":"","hd":false,"mn":"ADBE Vector Graphic - Stroke","nm":"Stroke 1","lc":1,"lj":2,"ml":1,"o":{"a":0,"k":100,"ix":4},"w":{"a":0,"k":1.5,"ix":5},"d":[],"c":{"a":0,"k":[0.0588,0.0902,0.1647],"ix":3}},{"ty":"fl","bm":0,"cl":"","ln":"","hd":false,"mn":"ADBE Vector Graphic - Fill","nm":"Fill 1","c":{"a":0,"k":[1,1,1],"ix":4},"r":1,"o":{"a":0,"k":100,"ix":5}},{"ty":"tr","a":{"a":0,"k":[0,0],"ix":1},"s":{"a":0,"k":[100,100],"ix":3},"sk":{"a":0,"k":0,"ix":4},"p":{"a":0,"k":[784.181,821.718],"ix":2},"r":{"a":0,"k":0,"ix":6},"sa":{"a":0,"k":0,"ix":5},"o":{"a":0,"k":100,"ix":7}}]},{"ty":"tr","a":{"a":0,"k":[836.06,958.431],"ix":1},"s":{"a":0,"k":[100,100],"ix":3},"sk":{"a":0,"k":0,"ix":4},"p":{"a":0,"k":[836.06,958.431],"ix":2},"r":{"a":1,"k":[{"o":{"x":0.333,"y":0},"i":{"x":0.667,"y":1},"s":[0],"t":0},{"o":{"x":0.333,"y":0},"i":{"x":0.667,"y":1},"s":[-11],"t":90},{"o":{"x":0.167,"y":0.167},"i":{"x":0.833,"y":0.833},"s":[0],"t":179}],"ix":6},"sa":{"a":0,"k":0,"ix":5},"o":{"a":0,"k":100,"ix":7}}]},{"ty":"gr","bm":0,"cl":"","ln":"","hd":false,"mn":"ADBE Vector Group","nm":"Group 22","ix":4,"cix":2,"np":3,"it":[{"ty":"gr","bm":0,"cl":"","ln":"","hd":false,"mn":"ADBE Vector Group","nm":"Group 10","ix":1,"cix":2,"np":2,"it":[{"ty":"sh","bm":0,"cl":"","ln":"","hd":false,"mn":"ADBE Vector Shape - Group","nm":"Path 1","ix":1,"d":1,"ks":{"a":0,"k":{"c":false,"i":[[0,0],[-61.426,-76.687]],"o":[[0,0],[0,0]],"v":[[-84.632,-57.885],[84.632,57.884]]},"ix":2}},{"ty":"st","bm":0,"cl":"","ln":"","hd":false,"mn":"ADBE Vector Graphic - Stroke","nm":"Stroke 1","lc":1,"lj":2,"ml":1,"o":{"a":0,"k":100,"ix":4},"w":{"a":0,"k":1.5,"ix":5},"d":[],"c":{"a":0,"k":[0.0588,0.0902,0.1647],"ix":3}},{"ty":"tr","a":{"a":0,"k":[0,0],"ix":1},"s":{"a":0,"k":[100,100],"ix":3},"sk":{"a":0,"k":0,"ix":4},"p":{"a":0,"k":[702.072,922.441],"ix":2},"r":{"a":0,"k":0,"ix":6},"sa":{"a":0,"k":0,"ix":5},"o":{"a":0,"k":100,"ix":7}}]},{"ty":"gr","bm":0,"cl":"","ln":"","hd":false,"mn":"ADBE Vector Group","nm":"Group 11","ix":2,"cix":2,"np":3,"it":[{"ty":"sh","bm":0,"cl":"","ln":"","hd":false,"mn":"ADBE Vector Shape - Group","nm":"Path 1","ix":1,"d":1,"ks":{"a":0,"k":{"c":true,"i":[[4.364,-0.96],[-33.203,-22.495],[0,0],[-0.437,-0.286],[-13.074,-5.635],[0,0],[-1.365,-0.538],[-18.443,-3.608],[34.64,21.617]],"o":[[0,0],[0.474,0.32],[0,0],[9.63,6.303],[1.039,0.448],[0,0],[14.16,5.574],[0,0],[-31.677,-19.767]],"v":[[-68.52,-40.531],[-22.656,4.814],[-13.111,-0.307],[-19.924,6.633],[14.044,24.794],[20.293,16.728],[21.844,27.74],[68.519,41.49],[2.265,-6.174]]},"ix":2}},{"ty":"st","bm":0,"cl":"","ln":"","hd":false,"mn":"ADBE Vector Graphic - Stroke","nm":"Stroke 1","lc":1,"lj":2,"ml":1,"o":{"a":0,"k":100,"ix":4},"w":{"a":0,"k":1.5,"ix":5},"d":[],"c":{"a":0,"k":[0.0588,0.0902,0.1647],"ix":3}},{"ty":"fl","bm":0,"cl":"","ln":"","hd":false,"mn":"ADBE Vector Graphic - Fill","nm":"Fill 1","c":{"a":0,"k":[0.0588,0.0902,0.1647],"ix":4},"r":1,"o":{"a":0,"k":100,"ix":5}},{"ty":"tr","a":{"a":0,"k":[0,0],"ix":1},"s":{"a":0,"k":[100,100],"ix":3},"sk":{"a":0,"k":0,"ix":4},"p":{"a":0,"k":[685.937,905.172],"ix":2},"r":{"a":0,"k":0,"ix":6},"sa":{"a":0,"k":0,"ix":5},"o":{"a":0,"k":100,"ix":7}}]},{"ty":"gr","bm":0,"cl":"","ln":"","hd":false,"mn":"ADBE Vector Group","nm":"Group 12","ix":3,"cix":2,"np":3,"it":[{"ty":"sh","bm":0,"cl":"","ln":"","hd":false,"mn":"ADBE Vector Shape - Group","nm":"Path 1","ix":1,"d":1,"ks":{"a":0,"k":{"c":true,"i":[[9.137,-2.01],[-33.203,-22.495],[0,0],[-0.437,-0.286],[-13.074,-5.635],[0,0],[-1.365,-0.538],[-18.443,-3.608],[9.838,14.056],[0,0],[0.483,0.649],[10.697,8.989],[0,0],[0.744,0.578],[21.871,2.205],[0,0],[1.293,0.034]],"o":[[0,0],[0.474,0.32],[0,0],[9.63,6.303],[1.039,0.448],[0,0],[14.16,5.574],[0,0],[-0.582,-0.832],[0,0],[-6.819,-9.177],[-0.629,-0.529],[0,0],[-14.95,-11.617],[-1.174,-0.119],[0,0],[-8.225,-0.213]],"v":[[-68.52,-39.612],[-22.656,5.732],[-13.111,0.612],[-19.924,7.551],[14.044,25.713],[20.293,17.646],[21.844,28.659],[68.519,42.409],[54.241,18.06],[45.5,16.803],[50.312,12.599],[24.266,-15.322],[14.38,-9.519],[20.153,-18.648],[-35.082,-41.727],[-37.108,-31.027],[-42.478,-42.195]]},"ix":2}},{"ty":"st","bm":0,"cl":"","ln":"","hd":false,"mn":"ADBE Vector Graphic - Stroke","nm":"Stroke 1","lc":1,"lj":2,"ml":1,"o":{"a":0,"k":100,"ix":4},"w":{"a":0,"k":1.5,"ix":5},"d":[],"c":{"a":0,"k":[0.0588,0.0902,0.1647],"ix":3}},{"ty":"fl","bm":0,"cl":"","ln":"","hd":false,"mn":"ADBE Vector Graphic - Fill","nm":"Fill 1","c":{"a":0,"k":[1,1,1],"ix":4},"r":1,"o":{"a":0,"k":100,"ix":5}},{"ty":"tr","a":{"a":0,"k":[0,0],"ix":1},"s":{"a":0,"k":[100,100],"ix":3},"sk":{"a":0,"k":0,"ix":4},"p":{"a":0,"k":[685.937,904.254],"ix":2},"r":{"a":0,"k":0,"ix":6},"sa":{"a":0,"k":0,"ix":5},"o":{"a":0,"k":100,"ix":7}}]},{"ty":"tr","a":{"a":0,"k":[787.061,982.175],"ix":1},"s":{"a":0,"k":[100,100],"ix":3},"sk":{"a":0,"k":0,"ix":4},"p":{"a":0,"k":[787.061,982.175],"ix":2},"r":{"a":1,"k":[{"o":{"x":0.333,"y":0},"i":{"x":0.667,"y":1},"s":[9],"t":0},{"o":{"x":0.333,"y":0},"i":{"x":0.667,"y":1},"s":[0],"t":90},{"o":{"x":0.167,"y":0.167},"i":{"x":0.833,"y":0.833},"s":[9],"t":179}],"ix":6},"sa":{"a":0,"k":0,"ix":5},"o":{"a":0,"k":100,"ix":7}}]},{"ty":"gr","bm":0,"cl":"","ln":"","hd":false,"mn":"ADBE Vector Group","nm":"Group 23","ix":5,"cix":2,"np":3,"it":[{"ty":"gr","bm":0,"cl":"","ln":"","hd":false,"mn":"ADBE Vector Group","nm":"Group 13","ix":1,"cix":2,"np":2,"it":[{"ty":"sh","bm":0,"cl":"","ln":"","hd":false,"mn":"ADBE Vector Shape - Group","nm":"Path 1","ix":1,"d":1,"ks":{"a":0,"k":{"c":false,"i":[[0,0],[76.737,-95.802]],"o":[[0,0],[0,0]],"v":[[105.728,-72.312],[-105.727,72.312]]},"ix":2}},{"ty":"st","bm":0,"cl":"","ln":"","hd":false,"mn":"ADBE Vector Graphic - Stroke","nm":"Stroke 1","lc":1,"lj":2,"ml":1,"o":{"a":0,"k":100,"ix":4},"w":{"a":0,"k":1.5,"ix":5},"d":[],"c":{"a":0,"k":[0.0588,0.0902,0.1647],"ix":3}},{"ty":"tr","a":{"a":0,"k":[0,0],"ix":1},"s":{"a":0,"k":[100,100],"ix":3},"sk":{"a":0,"k":0,"ix":4},"p":{"a":0,"k":[955.129,909.366],"ix":2},"r":{"a":0,"k":0,"ix":6},"sa":{"a":0,"k":0,"ix":5},"o":{"a":0,"k":100,"ix":7}}]},{"ty":"gr","bm":0,"cl":"","ln":"","hd":false,"mn":"ADBE Vector Group","nm":"Group 14","ix":2,"cix":2,"np":3,"it":[{"ty":"sh","bm":0,"cl":"","ln":"","hd":false,"mn":"ADBE Vector Shape - Group","nm":"Path 1","ix":1,"d":1,"ks":{"a":0,"k":{"c":true,"i":[[-5.452,-1.199],[41.48,-28.101],[0,0],[0.545,-0.356],[16.332,-7.04],[0,0],[1.705,-0.671],[23.041,-4.509],[-43.274,27.004]],"o":[[0,0],[-0.591,0.401],[0,0],[-12.031,7.874],[-1.297,0.56],[0,0],[-17.69,6.964],[0,0],[39.573,-24.694]],"v":[[85.599,-50.634],[28.302,6.012],[16.378,-0.384],[24.89,8.284],[-17.546,30.974],[-25.352,20.896],[-27.29,34.653],[-85.6,51.833],[-2.831,-7.714]]},"ix":2}},{"ty":"st","bm":0,"cl":"","ln":"","hd":false,"mn":"ADBE Vector Graphic - Stroke","nm":"Stroke 1","lc":1,"lj":2,"ml":1,"o":{"a":0,"k":100,"ix":4},"w":{"a":0,"k":1.5,"ix":5},"d":[],"c":{"a":0,"k":[0.0588,0.0902,0.1647],"ix":3}},{"ty":"fl","bm":0,"cl":"","ln":"","hd":false,"mn":"ADBE Vector Graphic - Fill","nm":"Fill 1","c":{"a":0,"k":[0.0588,0.0902,0.1647],"ix":4},"r":1,"o":{"a":0,"k":100,"ix":5}},{"ty":"tr","a":{"a":0,"k":[0,0],"ix":1},"s":{"a":0,"k":[100,100],"ix":3},"sk":{"a":0,"k":0,"ix":4},"p":{"a":0,"k":[975.287,887.794],"ix":2},"r":{"a":0,"k":0,"ix":6},"sa":{"a":0,"k":0,"ix":5},"o":{"a":0,"k":100,"ix":7}}]},{"ty":"gr","bm":0,"cl":"","ln":"","hd":false,"mn":"ADBE Vector Group","nm":"Group 15","ix":3,"cix":2,"np":3,"it":[{"ty":"sh","bm":0,"cl":"","ln":"","hd":false,"mn":"ADBE Vector Shape - Group","nm":"Path 1","ix":1,"d":1,"ks":{"a":0,"k":{"c":true,"i":[[-11.415,-2.512],[41.48,-28.101],[0,0],[0.545,-0.356],[16.332,-7.04],[0,0],[1.705,-0.671],[23.041,-4.509],[-12.29,17.56],[0,0],[-0.604,0.811],[-13.363,11.23],[0,0],[-0.93,0.723],[-27.324,2.756],[0,0],[-1.616,0.042]],"o":[[0,0],[-0.591,0.401],[0,0],[-12.031,7.874],[-1.297,0.56],[0,0],[-17.69,6.964],[0,0],[0.726,-1.038],[0,0],[8.519,-11.464],[0.785,-0.66],[0,0],[18.677,-14.512],[1.465,-0.148],[0,0],[10.274,-0.265]],"v":[[85.599,-49.487],[28.302,7.159],[16.378,0.763],[24.89,9.431],[-17.546,32.121],[-25.352,22.043],[-27.29,35.8],[-85.6,52.98],[-67.762,22.559],[-56.842,20.99],[-62.854,15.738],[-30.316,-19.143],[-17.966,-11.893],[-25.177,-23.299],[43.827,-52.131],[46.356,-38.762],[53.066,-52.715]]},"ix":2}},{"ty":"st","bm":0,"cl":"","ln":"","hd":false,"mn":"ADBE Vector Graphic - Stroke","nm":"Stroke 1","lc":1,"lj":2,"ml":1,"o":{"a":0,"k":100,"ix":4},"w":{"a":0,"k":1.5,"ix":5},"d":[],"c":{"a":0,"k":[0.0588,0.0902,0.1647],"ix":3}},{"ty":"fl","bm":0,"cl":"","ln":"","hd":false,"mn":"ADBE Vector Graphic - Fill","nm":"Fill 1","c":{"a":0,"k":[1,1,1],"ix":4},"r":1,"o":{"a":0,"k":100,"ix":5}},{"ty":"tr","a":{"a":0,"k":[0,0],"ix":1},"s":{"a":0,"k":[100,100],"ix":3},"sk":{"a":0,"k":0,"ix":4},"p":{"a":0,"k":[975.287,886.647],"ix":2},"r":{"a":0,"k":0,"ix":6},"sa":{"a":0,"k":0,"ix":5},"o":{"a":0,"k":100,"ix":7}}]},{"ty":"tr","a":{"a":0,"k":[849.144,980.784],"ix":1},"s":{"a":0,"k":[100,100],"ix":3},"sk":{"a":0,"k":0,"ix":4},"p":{"a":0,"k":[849.144,980.784],"ix":2},"r":{"a":1,"k":[{"o":{"x":0.333,"y":0},"i":{"x":0.667,"y":1},"s":[0],"t":0},{"o":{"x":0.333,"y":0},"i":{"x":0.667,"y":1},"s":[8],"t":90},{"o":{"x":0.167,"y":0.167},"i":{"x":0.833,"y":0.833},"s":[0],"t":179}],"ix":6},"sa":{"a":0,"k":0,"ix":5},"o":{"a":0,"k":100,"ix":7}}]},{"ty":"gr","bm":0,"cl":"","ln":"","hd":false,"mn":"ADBE Vector Group","nm":"Group 24","ix":6,"cix":2,"np":3,"it":[{"ty":"gr","bm":0,"cl":"","ln":"","hd":false,"mn":"ADBE Vector Group","nm":"Group 16","ix":1,"cix":2,"np":2,"it":[{"ty":"sh","bm":0,"cl":"","ln":"","hd":false,"mn":"ADBE Vector Shape - Group","nm":"Path 1","ix":1,"d":1,"ks":{"a":0,"k":{"c":false,"i":[[0,0],[35.794,-172.343]],"o":[[0,0],[0,0]],"v":[[88.12,-161.169],[-88.121,161.169]]},"ix":2}},{"ty":"st","bm":0,"cl":"","ln":"","hd":false,"mn":"ADBE Vector Graphic - Stroke","nm":"Stroke 1","lc":1,"lj":2,"ml":1,"o":{"a":0,"k":100,"ix":4},"w":{"a":0,"k":1.5,"ix":5},"d":[],"c":{"a":0,"k":[0.0588,0.0902,0.1647],"ix":3}},{"ty":"tr","a":{"a":0,"k":[0,0],"ix":1},"s":{"a":0,"k":[100,100],"ix":3},"sk":{"a":0,"k":0,"ix":4},"p":{"a":0,"k":[938.395,818.118],"ix":2},"r":{"a":0,"k":0,"ix":6},"sa":{"a":0,"k":0,"ix":5},"o":{"a":0,"k":100,"ix":7}}]},{"ty":"gr","bm":0,"cl":"","ln":"","hd":false,"mn":"ADBE Vector Group","nm":"Group 17","ix":2,"cix":2,"np":3,"it":[{"ty":"sh","bm":0,"cl":"","ln":"","hd":false,"mn":"ADBE Vector Shape - Group","nm":"Path 1","ix":1,"d":1,"ks":{"a":0,"k":{"c":true,"i":[[-7.748,2.012],[34.746,-62.887],[0,0],[0.465,-0.811],[16.297,-19.617],[0,0],[1.743,-1.966],[26.518,-20.743],[-37.753,62.652]],"o":[[0,0],[-0.495,0.896],[0,0],[-10.259,17.885],[-1.295,1.559],[0,0],[-18.083,20.403],[0,0],[34.524,-57.293]],"v":[[76.098,-121.139],[39.695,-11.482],[20.295,-11.907],[36.811,-6.36],[-2.676,50.232],[-19.207,42.426],[-12.739,61.269],[-76.098,121.139],[-9.023,-8.785]]},"ix":2}},{"ty":"st","bm":0,"cl":"","ln":"","hd":false,"mn":"ADBE Vector Graphic - Stroke","nm":"Stroke 1","lc":1,"lj":2,"ml":1,"o":{"a":0,"k":100,"ix":4},"w":{"a":0,"k":1.5,"ix":5},"d":[],"c":{"a":0,"k":[0.0588,0.0902,0.1647],"ix":3}},{"ty":"fl","bm":0,"cl":"","ln":"","hd":false,"mn":"ADBE Vector Graphic - Fill","nm":"Fill 1","c":{"a":0,"k":[0.0588,0.0902,0.1647],"ix":4},"r":1,"o":{"a":0,"k":100,"ix":5}},{"ty":"tr","a":{"a":0,"k":[0,0],"ix":1},"s":{"a":0,"k":[100,100],"ix":3},"sk":{"a":0,"k":0,"ix":4},"p":{"a":0,"k":[950.524,778.204],"ix":2},"r":{"a":0,"k":0,"ix":6},"sa":{"a":0,"k":0,"ix":5},"o":{"a":0,"k":100,"ix":7}}]},{"ty":"gr","bm":0,"cl":"","ln":"","hd":false,"mn":"ADBE Vector Group","nm":"Group 18","ix":3,"cix":2,"np":3,"it":[{"ty":"sh","bm":0,"cl":"","ln":"","hd":false,"mn":"ADBE Vector Shape - Group","nm":"Path 1","ix":1,"d":1,"ks":{"a":0,"k":{"c":true,"i":[[-16.222,4.212],[34.746,-62.887],[0,0],[0.465,-0.811],[16.297,-19.617],[0,0],[1.743,-1.966],[26.518,-20.743],[-4.292,30.434],[0,0],[-0.244,1.429],[-9.778,23.042],[0,0],[-0.717,1.527],[-33.133,21.288],[0,0],[-2.037,1.105]],"o":[[0,0],[-0.495,0.896],[0,0],[-10.259,17.885],[-1.295,1.559],[0,0],[-18.083,20.403],[0,0],[0.254,-1.8],[0,0],[3.436,-20.193],[0.575,-1.355],[0,0],[14.437,-30.693],[1.777,-1.141],[0,0],[12.96,-7.019]],"v":[[76.734,-121.139],[40.331,-11.482],[20.931,-11.907],[37.447,-6.36],[-2.04,50.232],[-18.571,42.426],[-12.103,61.269],[-75.462,121.139],[-72.442,70.66],[-59.505,61.553],[-70.604,58.75],[-51.695,-6.989],[-31.196,-5.752],[-47.828,-15.641],[21.625,-97.359],[33.549,-81.916],[33.053,-104.112]]},"ix":2}},{"ty":"st","bm":0,"cl":"","ln":"","hd":false,"mn":"ADBE Vector Graphic - Stroke","nm":"Stroke 1","lc":1,"lj":2,"ml":1,"o":{"a":0,"k":100,"ix":4},"w":{"a":0,"k":1.5,"ix":5},"d":[],"c":{"a":0,"k":[0.0588,0.0902,0.1647],"ix":3}},{"ty":"fl","bm":0,"cl":"","ln":"","hd":false,"mn":"ADBE Vector Graphic - Fill","nm":"Fill 1","c":{"a":0,"k":[1,1,1],"ix":4},"r":1,"o":{"a":0,"k":100,"ix":5}},{"ty":"tr","a":{"a":0,"k":[0,0],"ix":1},"s":{"a":0,"k":[100,100],"ix":3},"sk":{"a":0,"k":0,"ix":4},"p":{"a":0,"k":[949.888,778.204],"ix":2},"r":{"a":0,"k":0,"ix":6},"sa":{"a":0,"k":0,"ix":5},"o":{"a":0,"k":100,"ix":7}}]},{"ty":"tr","a":{"a":0,"k":[850.448,979.118],"ix":1},"s":{"a":0,"k":[100,100],"ix":3},"sk":{"a":0,"k":0,"ix":4},"p":{"a":0,"k":[850.448,979.118],"ix":2},"r":{"a":1,"k":[{"o":{"x":0.333,"y":0},"i":{"x":0.667,"y":1},"s":[0],"t":0},{"o":{"x":0.333,"y":0},"i":{"x":0.667,"y":1},"s":[4],"t":90},{"o":{"x":0.167,"y":0.167},"i":{"x":0.833,"y":0.833},"s":[0],"t":179}],"ix":6},"sa":{"a":0,"k":0,"ix":5},"o":{"a":0,"k":100,"ix":7}}]}],"ind":1},{"ty":4,"nm":"shape1","mn":"","sr":1,"st":0,"op":180,"ip":0,"hd":false,"cl":"","ln":"","ddd":0,"bm":0,"hasMask":false,"ao":0,"ks":{"a":{"a":0,"k":[637.747,475.31,0],"ix":1},"s":{"a":0,"k":[100,100,100],"ix":6},"sk":{"a":0,"k":0},"p":{"a":0,"k":[637.747,475.31,0],"ix":2},"r":{"a":0,"k":0,"ix":10},"sa":{"a":0,"k":0},"o":{"a":0,"k":100,"ix":11}},"ef":[],"shapes":[{"ty":"gr","bm":0,"cl":"","ln":"","hd":false,"mn":"ADBE Vector Group","nm":"Group 1","ix":1,"cix":2,"np":3,"it":[{"ty":"sh","bm":0,"cl":"","ln":"","hd":false,"mn":"ADBE Vector Shape - Group","nm":"Path 1","ix":1,"d":1,"ks":{"a":0,"k":{"c":true,"i":[[0.331,0.331],[0.471,0],[0,0],[0.331,-0.332],[0,-0.47],[0,0],[-0.331,-0.331],[-0.469,0],[0,0],[-0.331,0.331],[0,0.47],[0,0]],"o":[[-0.331,-0.333],[0,0],[-0.469,0],[-0.332,0.331],[0,0],[0,0.47],[0.332,0.332],[0,0],[0.469,0],[0.332,-0.332],[0,0],[0,-0.469]],"v":[[18.433,-4.918],[17.172,-5.441],[-17.171,-5.441],[-18.431,-4.919],[-18.953,-3.659],[-18.953,3.66],[-18.431,4.92],[-17.171,5.441],[17.172,5.441],[18.432,4.921],[18.954,3.66],[18.954,-3.659]]},"ix":2}},{"ty":"st","bm":0,"cl":"","ln":"","hd":false,"mn":"ADBE Vector Graphic - Stroke","nm":"Stroke 1","lc":1,"lj":1,"ml":10,"o":{"a":0,"k":100,"ix":4},"w":{"a":0,"k":1.5,"ix":5},"d":[],"c":{"a":0,"k":[0.0588,0.0902,0.1647],"ix":3}},{"ty":"fl","bm":0,"cl":"","ln":"","hd":false,"mn":"ADBE Vector Graphic - Fill","nm":"Fill 1","c":{"a":0,"k":[0.0588,0.0902,0.1647],"ix":4},"r":1,"o":{"a":0,"k":100,"ix":5}},{"ty":"tr","a":{"a":0,"k":[0,0],"ix":1},"s":{"a":0,"k":[100,100],"ix":3},"sk":{"a":0,"k":0,"ix":4},"p":{"a":1,"k":[{"o":{"x":0.333,"y":0},"i":{"x":0.667,"y":1},"s":[917.965,640.763],"t":0,"ti":[0,0],"to":[5.667,0]},{"o":{"x":0.333,"y":0},"i":{"x":0.667,"y":1},"s":[951.965,640.763],"t":90,"ti":[5.667,0],"to":[0,0]},{"o":{"x":0.167,"y":0.167},"i":{"x":0.833,"y":0.833},"s":[917.965,640.763],"t":179}],"ix":2},"r":{"a":0,"k":0,"ix":6},"sa":{"a":0,"k":0,"ix":5},"o":{"a":0,"k":100,"ix":7}}]},{"ty":"gr","bm":0,"cl":"","ln":"","hd":false,"mn":"ADBE Vector Group","nm":"Group 2","ix":2,"cix":2,"np":3,"it":[{"ty":"sh","bm":0,"cl":"","ln":"","hd":false,"mn":"ADBE Vector Shape - Group","nm":"Path 1","ix":1,"d":1,"ks":{"a":0,"k":{"c":true,"i":[[0.332,0.332],[0,0],[0.47,0],[0,0],[0,0],[0.331,0.331],[0.469,0],[0,0],[0.332,-0.332],[0,-0.469],[0,0],[0,0],[0.334,-0.333],[0,-0.469],[0,0],[-0.332,-0.331],[-0.469,0],[0,0],[0,0],[-0.33,-0.33],[-0.471,0],[0,0],[-0.33,0.331],[0,0.47],[0,0],[0,0],[-0.332,0.331],[0,0.469],[0,0]],"o":[[0,0],[-0.332,-0.332],[0,0],[0,0],[0,-0.469],[-0.332,-0.332],[0,0],[-0.469,0],[-0.332,0.331],[0,0],[0,0],[-0.468,0],[-0.331,0.333],[0,0],[0,0.469],[0.331,0.332],[0,0],[0,0],[0,0.47],[0.332,0.332],[0,0],[0.469,0],[0.332,-0.332],[0,0],[0,0],[0.469,0],[0.333,-0.332],[0,0],[0,-0.469]],"v":[[18.432,-4.919],[18.432,-4.92],[17.171,-5.442],[5.442,-5.442],[5.442,-17.172],[4.92,-18.432],[3.66,-18.954],[-3.659,-18.954],[-4.92,-18.432],[-5.442,-17.172],[-5.442,-5.442],[-17.172,-5.442],[-18.433,-4.919],[-18.954,-3.659],[-18.954,3.66],[-18.431,4.92],[-17.172,5.442],[-5.442,5.442],[-5.442,17.172],[-4.921,18.431],[-3.659,18.954],[3.66,18.954],[4.919,18.433],[5.442,17.172],[5.442,5.442],[17.171,5.442],[18.431,4.921],[18.954,3.66],[18.954,-3.659]]},"ix":2}},{"ty":"st","bm":0,"cl":"","ln":"","hd":false,"mn":"ADBE Vector Graphic - Stroke","nm":"Stroke 1","lc":1,"lj":1,"ml":10,"o":{"a":0,"k":100,"ix":4},"w":{"a":0,"k":1.5,"ix":5},"d":[],"c":{"a":0,"k":[0.0588,0.0902,0.1647],"ix":3}},{"ty":"fl","bm":0,"cl":"","ln":"","hd":false,"mn":"ADBE Vector Graphic - Fill","nm":"Fill 1","c":{"a":0,"k":[0.0588,0.0902,0.1647],"ix":4},"r":1,"o":{"a":0,"k":100,"ix":5}},{"ty":"tr","a":{"a":0,"k":[0,0],"ix":1},"s":{"a":0,"k":[100,100],"ix":3},"sk":{"a":0,"k":0,"ix":4},"p":{"a":0,"k":[357.529,323.37],"ix":2},"r":{"a":1,"k":[{"o":{"x":0.167,"y":0.167},"i":{"x":0.833,"y":0.833},"s":[0],"t":0},{"o":{"x":0.167,"y":0.167},"i":{"x":0.833,"y":0.833},"s":[360],"t":179}],"ix":6},"sa":{"a":0,"k":0,"ix":5},"o":{"a":0,"k":100,"ix":7}}]}],"ind":2},{"ty":4,"nm":"shape2","mn":"","sr":1,"st":0,"op":180,"ip":0,"hd":false,"cl":"","ln":"","ddd":0,"bm":0,"hasMask":false,"ao":0,"ks":{"a":{"a":0,"k":[622.876,761.657,0],"ix":1},"s":{"a":0,"k":[100,100,100],"ix":6},"sk":{"a":0,"k":0},"p":{"a":0,"k":[622.876,761.657,0],"ix":2},"r":{"a":0,"k":0,"ix":10},"sa":{"a":0,"k":0},"o":{"a":0,"k":100,"ix":11}},"ef":[],"shapes":[{"ty":"gr","bm":0,"cl":"","ln":"","hd":false,"mn":"ADBE Vector Group","nm":"Group 1","ix":1,"cix":2,"np":2,"it":[{"ty":"sh","bm":0,"cl":"","ln":"","hd":false,"mn":"ADBE Vector Shape - Group","nm":"Path 1","ix":1,"d":1,"ks":{"a":0,"k":{"c":true,"i":[[0,-9.063],[-9.064,0],[0,9.063],[9.065,0]],"o":[[0,9.063],[9.065,0],[0,-9.063],[-9.064,0]],"v":[[-16.412,0],[0,16.409],[16.412,0],[0,-16.409]]},"ix":2}},{"ty":"fl","bm":0,"cl":"","ln":"","hd":false,"mn":"ADBE Vector Graphic - Fill","nm":"Fill 1","c":{"a":0,"k":[0.9216,0.9216,0.9216],"ix":4},"r":1,"o":{"a":0,"k":100,"ix":5}},{"ty":"tr","a":{"a":0,"k":[0,0],"ix":1},"s":{"a":0,"k":[100,100],"ix":3},"sk":{"a":0,"k":0,"ix":4},"p":{"a":0,"k":[882.331,684.014],"ix":2},"r":{"a":0,"k":0,"ix":6},"sa":{"a":0,"k":0,"ix":5},"o":{"a":0,"k":100,"ix":7}}]},{"ty":"gr","bm":0,"cl":"","ln":"","hd":false,"mn":"ADBE Vector Group","nm":"Group 2","ix":2,"cix":2,"np":2,"it":[{"ty":"sh","bm":0,"cl":"","ln":"","hd":false,"mn":"ADBE Vector Shape - Group","nm":"Path 1","ix":1,"d":1,"ks":{"a":0,"k":{"c":true,"i":[[-10.977,10.975],[10.977,10.974],[10.977,-10.976],[-10.977,-10.976]],"o":[[10.977,-10.976],[-10.977,-10.976],[-10.977,10.974],[10.977,10.975]],"v":[[19.875,19.872],[19.875,-19.871],[-19.875,-19.871],[-19.875,19.872]]},"ix":2}},{"ty":"fl","bm":0,"cl":"","ln":"","hd":false,"mn":"ADBE Vector Graphic - Fill","nm":"Fill 1","c":{"a":0,"k":[0.9216,0.9216,0.9216],"ix":4},"r":1,"o":{"a":0,"k":100,"ix":5}},{"ty":"tr","a":{"a":0,"k":[0,0],"ix":1},"s":{"a":0,"k":[100,100],"ix":3},"sk":{"a":0,"k":0,"ix":4},"p":{"a":0,"k":[375.117,827.607],"ix":2},"r":{"a":0,"k":0,"ix":6},"sa":{"a":0,"k":0,"ix":5},"o":{"a":0,"k":100,"ix":7}}]}],"ind":3},{"ty":4,"nm":"letters","mn":"","sr":1,"st":0,"op":180,"ip":0,"hd":false,"cl":"","ln":"","ddd":0,"bm":0,"hasMask":false,"ao":0,"ks":{"a":{"a":0,"k":[248.668,548.951,0],"ix":1},"s":{"a":0,"k":[100,100,100],"ix":6},"sk":{"a":0,"k":0},"p":{"a":0,"k":[248.668,548.951,0],"ix":2},"r":{"a":1,"k":[{"o":{"x":0.333,"y":0},"i":{"x":0.667,"y":1},"s":[15],"t":0},{"o":{"x":0.333,"y":0},"i":{"x":0.667,"y":1},"s":[-7],"t":90},{"o":{"x":0.167,"y":0.167},"i":{"x":0.833,"y":0.833},"s":[15],"t":179}],"ix":10},"sa":{"a":0,"k":0},"o":{"a":0,"k":100,"ix":11}},"ef":[],"shapes":[{"ty":"gr","bm":0,"cl":"","ln":"","hd":false,"mn":"ADBE Vector Group","nm":"Group 1","ix":1,"cix":2,"np":2,"it":[{"ty":"sh","bm":0,"cl":"","ln":"","hd":false,"mn":"ADBE Vector Shape - Group","nm":"Path 1","ix":1,"d":1,"ks":{"a":0,"k":{"c":true,"i":[[0,0],[0,0],[0,0]],"o":[[0,0],[0,0],[0,0]],"v":[[26.667,-19.705],[-26.668,-24.419],[-3.663,24.419]]},"ix":2}},{"ty":"fl","bm":0,"cl":"","ln":"","hd":false,"mn":"ADBE Vector Graphic - Fill","nm":"Fill 1","c":{"a":0,"k":[0.7569,0.7451,0.7373],"ix":4},"r":1,"o":{"a":0,"k":100,"ix":5}},{"ty":"tr","a":{"a":0,"k":[0,0],"ix":1},"s":{"a":0,"k":[100,100],"ix":3},"sk":{"a":0,"k":0,"ix":4},"p":{"a":0,"k":[222.003,569.995],"ix":2},"r":{"a":0,"k":0,"ix":6},"sa":{"a":0,"k":0,"ix":5},"o":{"a":0,"k":100,"ix":7}}]},{"ty":"gr","bm":0,"cl":"","ln":"","hd":false,"mn":"ADBE Vector Group","nm":"Group 2","ix":2,"cix":2,"np":2,"it":[{"ty":"sh","bm":0,"cl":"","ln":"","hd":false,"mn":"ADBE Vector Shape - Group","nm":"Path 1","ix":1,"d":1,"ks":{"a":0,"k":{"c":true,"i":[[0,0],[0,0],[0,0]],"o":[[0,0],[0,0],[0,0]],"v":[[26.666,24.419],[3.661,-24.419],[-26.666,19.706]]},"ix":2}},{"ty":"fl","bm":0,"cl":"","ln":"","hd":false,"mn":"ADBE Vector Graphic - Fill","nm":"Fill 1","c":{"a":0,"k":[0.7569,0.7451,0.7373],"ix":4},"r":1,"o":{"a":0,"k":100,"ix":5}},{"ty":"tr","a":{"a":0,"k":[0,0],"ix":1},"s":{"a":0,"k":[100,100],"ix":3},"sk":{"a":0,"k":0,"ix":4},"p":{"a":0,"k":[275.336,530.585],"ix":2},"r":{"a":0,"k":0,"ix":6},"sa":{"a":0,"k":0,"ix":5},"o":{"a":0,"k":100,"ix":7}}]},{"ty":"gr","bm":0,"cl":"","ln":"","hd":false,"mn":"ADBE Vector Group","nm":"Group 3","ix":3,"cix":2,"np":2,"it":[{"ty":"sh","bm":0,"cl":"","ln":"","hd":false,"mn":"ADBE Vector Shape - Group","nm":"Path 1","ix":1,"d":1,"ks":{"a":0,"k":{"c":true,"i":[[0,0],[0,0],[0,0],[0,0],[0,0]],"o":[[0,0],[0,0],[0,0],[0,0],[0,0]],"v":[[30.329,-42.786],[-22.044,-45.464],[-53.333,-3.375],[-30.327,45.464],[53.333,6.052]]},"ix":2}},{"ty":"fl","bm":0,"cl":"","ln":"","hd":false,"mn":"ADBE Vector Graphic - Fill","nm":"Fill 1","c":{"a":0,"k":[0.9216,0.9216,0.9216],"ix":4},"r":1,"o":{"a":0,"k":100,"ix":5}},{"ty":"tr","a":{"a":0,"k":[0,0],"ix":1},"s":{"a":0,"k":[100,100],"ix":3},"sk":{"a":0,"k":0,"ix":4},"p":{"a":0,"k":[248.668,548.951],"ix":2},"r":{"a":0,"k":0,"ix":6},"sa":{"a":0,"k":0,"ix":5},"o":{"a":0,"k":100,"ix":7}}]}],"ind":4},{"ty":3,"mn":"","sr":1,"st":0,"op":180,"ip":0,"hd":false,"cl":"","ln":"","ddd":0,"bm":0,"hasMask":false,"ao":0,"ks":{"a":{"a":0,"k":[917.966,491.37,0],"ix":1},"s":{"a":0,"k":[100,100,100],"ix":6},"sk":{"a":0,"k":0},"p":{"a":1,"k":[{"o":{"x":0.333,"y":0},"i":{"x":0.667,"y":1},"s":[917.966,491.37,0],"t":0,"ti":[0,0,0],"to":[0,4.333,0]},{"o":{"x":0.333,"y":0},"i":{"x":0.667,"y":1},"s":[917.966,517.37,0],"t":90,"ti":[0,4.333,0],"to":[0,0,0]},{"o":{"x":0.167,"y":0.167},"i":{"x":0.833,"y":0.833},"s":[917.966,491.37,0],"t":179}],"ix":2},"r":{"a":0,"k":0,"ix":10},"sa":{"a":0,"k":0},"o":{"a":0,"k":100,"ix":11}},"ind":5},{"ty":3,"mn":"","sr":1,"st":-5,"op":180,"ip":0,"hd":false,"cl":"","ln":"","ddd":0,"bm":0,"hasMask":false,"ao":0,"ks":{"a":{"a":0,"k":[280.921,1019.339,0],"ix":1},"s":{"a":0,"k":[100,100,100],"ix":6},"sk":{"a":0,"k":0},"p":{"a":0,"k":[280.921,1019.339,0],"ix":2},"r":{"a":0,"k":0,"ix":10},"sa":{"a":0,"k":0},"o":{"a":0,"k":100,"ix":11}},"ind":6},{"ty":4,"nm":"BG","mn":"","sr":1,"st":0,"op":180,"ip":0,"hd":false,"cl":"","ln":"","ddd":0,"bm":0,"hasMask":false,"ao":0,"ks":{"a":{"a":0,"k":[600,600,0],"ix":1},"s":{"a":0,"k":[100,100,100],"ix":6},"sk":{"a":0,"k":0},"p":{"a":0,"k":[600,600,0],"ix":2},"r":{"a":0,"k":0,"ix":10},"sa":{"a":0,"k":0},"o":{"a":0,"k":100,"ix":11}},"ef":[],"shapes":[{"ty":"gr","bm":0,"cl":"","ln":"","hd":false,"mn":"ADBE Vector Group","nm":"Group 1","ix":1,"cix":2,"np":2,"it":[{"ty":"sh","bm":0,"cl":"","ln":"","hd":false,"mn":"ADBE Vector Shape - Group","nm":"Path 1","ix":1,"d":1,"ks":{"a":0,"k":{"c":true,"i":[[0,0],[0,0],[0,0],[0,0]],"o":[[0,0],[0,0],[0,0],[0,0]],"v":[[382.929,0.867],[-382.928,0.867],[-382.928,-0.867],[382.929,-0.867]]},"ix":2}},{"ty":"fl","bm":0,"cl":"","ln":"","hd":false,"mn":"ADBE Vector Graphic - Fill","nm":"Fill 1","c":{"a":0,"k":[0.0588,0.0902,0.1647],"ix":4},"r":1,"o":{"a":0,"k":100,"ix":5}},{"ty":"tr","a":{"a":0,"k":[0,0],"ix":1},"s":{"a":0,"k":[100,100],"ix":3},"sk":{"a":0,"k":0,"ix":4},"p":{"a":0,"k":[523.833,732.714],"ix":2},"r":{"a":0,"k":0,"ix":6},"sa":{"a":0,"k":0,"ix":5},"o":{"a":0,"k":100,"ix":7}}]},{"ty":"gr","bm":0,"cl":"","ln":"","hd":false,"mn":"ADBE Vector Group","nm":"Group 2","ix":2,"cix":2,"np":2,"it":[{"ty":"sh","bm":0,"cl":"","ln":"","hd":false,"mn":"ADBE Vector Shape - Group","nm":"Path 1","ix":1,"d":1,"ks":{"a":0,"k":{"c":true,"i":[[0,0],[0,0],[0,0],[0,0]],"o":[[0,0],[0,0],[0,0],[0,0]],"v":[[453.979,1.42],[-453.979,1.42],[-453.979,-1.42],[453.979,-1.42]]},"ix":2}},{"ty":"fl","bm":0,"cl":"","ln":"","hd":false,"mn":"ADBE Vector Graphic - Fill","nm":"Fill 1","c":{"a":0,"k":[0.0588,0.0902,0.1647],"ix":4},"r":1,"o":{"a":0,"k":100,"ix":5}},{"ty":"tr","a":{"a":0,"k":[0,0],"ix":1},"s":{"a":0,"k":[100,100],"ix":3},"sk":{"a":0,"k":0,"ix":4},"p":{"a":0,"k":[580.62,1018.76],"ix":2},"r":{"a":0,"k":0,"ix":6},"sa":{"a":0,"k":0,"ix":5},"o":{"a":0,"k":100,"ix":7}}]},{"ty":"gr","bm":0,"cl":"","ln":"","hd":false,"mn":"ADBE Vector Group","nm":"Group 3","ix":3,"cix":2,"np":2,"it":[{"ty":"sh","bm":0,"cl":"","ln":"","hd":false,"mn":"ADBE Vector Shape - Group","nm":"Path 1","ix":1,"d":1,"ks":{"a":0,"k":{"c":true,"i":[[0,-9.79],[0.42,-1.51],[0.43,-0.911],[0,0],[0.36,0.969],[0,4.1],[-18.57,0],[-4.49,-13.29],[-0.59,0]],"o":[[0,1.65],[-0.27,0.98],[0,0],[-0.44,-0.92],[-1.34,-3.63],[0,-18.56],[14.8,0],[0.58,-0.06],[9.79,0]],"v":[[42.47,16.45],[41.82,21.21],[40.76,24.05],[-39.2,24.05],[-40.4,21.21],[-42.47,9.56],[-8.86,-24.05],[22.98,-1.19],[24.74,-1.28]]},"ix":2}},{"ty":"fl","bm":0,"cl":"","ln":"","hd":false,"mn":"ADBE Vector Graphic - Fill","nm":"Fill 1","c":{"a":0,"k":[0.7569,0.7451,0.7373],"ix":4},"r":1,"o":{"a":0,"k":100,"ix":5}},{"ty":"tr","a":{"a":0,"k":[0,0],"ix":1},"s":{"a":0,"k":[100,100],"ix":3},"sk":{"a":0,"k":0,"ix":4},"p":{"a":0,"k":[905.78,996.13],"ix":2},"r":{"a":0,"k":0,"ix":6},"sa":{"a":0,"k":0,"ix":5},"o":{"a":0,"k":100,"ix":7}}]},{"ty":"gr","bm":0,"cl":"","ln":"","hd":false,"mn":"ADBE Vector Group","nm":"Group 4","ix":4,"cix":2,"np":2,"it":[{"ty":"sh","bm":0,"cl":"","ln":"","hd":false,"mn":"ADBE Vector Shape - Group","nm":"Path 1","ix":1,"d":1,"ks":{"a":0,"k":{"c":true,"i":[[0,-36.98],[1.67,-5.839],[0.32,-0.939],[0,0],[0.17,0.96],[0,6.271],[-53.19,0],[-17.55,-18.549],[-3.63,0]],"o":[[0,6.38],[-0.27,0.96],[0,0],[-0.22,-0.939],[-1.15,-5.929],[0,-53.189],[27.56,0],[3.47,-0.549],[36.97,0]],"v":[[121.94,37.495],[119.38,55.894],[118.49,58.734],[-119.6,58.734],[-120.19,55.894],[-121.94,37.574],[-25.63,-58.734],[44.34,-28.606],[55,-29.455]]},"ix":2}},{"ty":"fl","bm":0,"cl":"","ln":"","hd":false,"mn":"ADBE Vector Graphic - Fill","nm":"Fill 1","c":{"a":0,"k":[0.9216,0.9216,0.9216],"ix":4},"r":1,"o":{"a":0,"k":100,"ix":5}},{"ty":"tr","a":{"a":0,"k":[0,0],"ix":1},"s":{"a":0,"k":[100,100],"ix":3},"sk":{"a":0,"k":0,"ix":4},"p":{"a":0,"k":[655.85,961.445],"ix":2},"r":{"a":0,"k":0,"ix":6},"sa":{"a":0,"k":0,"ix":5},"o":{"a":0,"k":100,"ix":7}}]}],"ind":7}],"id":"comp_1"}]}